{
    "id": "3ryID_SwU5E",
    "title": "$1 vs $100,000,000 House!",
    "publishedAt": "2023-10-14T16:00:00Z",
    "captions": [
        {
            "text": "This is a $100 million mega-mansion\nand it's possibly",
            "start": 0.033,
            "duration": 5.005
        },
        {
            "text": "the most luxurious house\never built by mankind.",
            "start": 5.038,
            "duration": 3.503
        },
        {
            "text": "And we're going to be comparing\nliving in this house",
            "start": 8.675,
            "duration": 2.336
        },
        {
            "text": "to living in this $69\nmillion art house",
            "start": 11.011,
            "duration": 3.203
        },
        {
            "text": "that's built to withstand\na literal tsunami,",
            "start": 14.214,
            "duration": 3.17
        },
        {
            "text": "a $30 million palace\nwith its very own waterpark",
            "start": 17.55,
            "duration": 3.99
        },
        {
            "text": "and everything in between,\nall the way down",
            "start": 22.522,
            "duration": 2.636
        },
        {
            "text": "to this $1 barely functioning house.",
            "start": 25.183,
            "duration": 3.493
        },
        {
            "text": "More of a shed.",
            "start": 28.854,
            "duration": 0.885
        },
        {
            "text": "Well, it's only a dollar.",
            "start": 29.763,
            "duration": 1.001
        },
        {
            "text": "Why does this house cost a dollar?",
            "start": 30.764,
            "duration": 1.601
        },
        {
            "text": "Yeah, we get another storm, it's\nprobably going to go into the water.",
            "start": 32.39,
            "duration": 2.596
        },
        {
            "text": "So it's worth a dollar for me\njust to get rid of it.",
            "start": 35.135,
            "duration": 2.335
        },
        {
            "text": "So you would say\nthis is a horrible investment for me?",
            "start": 37.537,
            "duration": 2.603
        },
        {
            "text": "- Yes, indeed.\n- Let's do it.",
            "start": 41.041,
            "duration": 1.796
        },
        {
            "text": "Let's go.",
            "start": 43.29,
            "duration": 1.187
        },
        {
            "text": "This is sketchy.",
            "start": 45.182,
            "duration": 1.231
        },
        {
            "text": "What are the odds I fall through?",
            "start": 46.413,
            "duration": 1.652
        },
        {
            "text": "Pretty high.",
            "start": 48.09,
            "duration": 0.982
        },
        {
            "text": "Bro, these are wobbly.",
            "start": 49.883,
            "duration": 1.134
        },
        {
            "text": "I like how that chair is just\nlike holding on for dear life.",
            "start": 51.017,
            "duration": 3.003
        },
        {
            "text": "We have a recliner, a mattress\nand half a floor.",
            "start": 54.02,
            "duration": 3.37
        },
        {
            "text": "I can literally fish\nfrom inside of the house.",
            "start": 57.524,
            "duration": 2.369
        },
        {
            "text": "Yo, I caught one.",
            "start": 60.093,
            "duration": 1.292
        },
        {
            "text": "That's just the lure. I'm sorry.",
            "start": 61.861,
            "duration": 2.069
        },
        {
            "text": "Now that you see us having fun,\ndo you regret selling it?",
            "start": 64.112,
            "duration": 1.987
        },
        {
            "text": "I do not.",
            "start": 66.299,
            "duration": 0.901
        },
        {
            "text": "What if I gave you $2 to buy\nback off me?",
            "start": 67.2,
            "duration": 2.402
        },
        {
            "text": "- No.\n- Alright, I tried.",
            "start": 69.69,
            "duration": 1.318
        },
        {
            "text": "I have an idea.",
            "start": 71.041,
            "duration": 0.764
        },
        {
            "text": "Let's get out of this house.",
            "start": 72.138,
            "duration": 1.068
        },
        {
            "text": "Later in this video,",
            "start": 73.206,
            "duration": 0.934
        },
        {
            "text": "we have a house that cost\n100 million times more than this.",
            "start": 74.14,
            "duration": 3.203
        },
        {
            "text": "And because I never plan on setting\nfoot in this worthless shack again...",
            "start": 77.343,
            "duration": 3.537
        },
        {
            "text": "Let's head\nover to something a little nicer.",
            "start": 82.348,
            "duration": 2.002
        },
        {
            "text": "Speaking of which, we're\nat the million dollar house,",
            "start": 85.151,
            "duration": 2.503
        },
        {
            "text": "which technically means you need to be\na millionaire to buy this house.",
            "start": 87.654,
            "duration": 3.103
        },
        {
            "text": "Let's show you\nhow a millionaire lives.",
            "start": 90.79,
            "duration": 1.869
        },
        {
            "text": "My first impression\nis it's way bigger than my house.",
            "start": 92.659,
            "duration": 2.969
        },
        {
            "text": "When you pay $1,000,000,\nyou get a pretty good sized kitchen,",
            "start": 95.628,
            "duration": 3.07
        },
        {
            "text": "along with four bedrooms\nthat look normal.",
            "start": 98.698,
            "duration": 2.569
        },
        {
            "text": "But they keep going",
            "start": 101.301,
            "duration": 1.234
        },
        {
            "text": "because this bedroom has a closet\nhere which leads into a bathroom",
            "start": 102.535,
            "duration": 3.037
        },
        {
            "text": "that's bigger than the $1 house.",
            "start": 105.572,
            "duration": 1.952
        },
        {
            "text": "The bathtub is gigantic.",
            "start": 107.549,
            "duration": 1.866
        },
        {
            "text": "I'm six foot five and I can fit\nin this perfectly comfortable.",
            "start": 109.44,
            "duration": 3.172
        },
        {
            "text": "And even though the bathrooms\nare all stocked with bidets",
            "start": 112.645,
            "duration": 2.603
        },
        {
            "text": "Oh God!",
            "start": 115.682,
            "duration": 1.114
        },
        {
            "text": "The best seat in\nthe house is definitely downstairs.",
            "start": 116.82,
            "duration": 2.365
        },
        {
            "text": "Oh snap! They have a movie theater.",
            "start": 119.219,
            "duration": 1.801
        },
        {
            "text": "Dude, these chairs are massage\nchairs.",
            "start": 121.02,
            "duration": 2.103
        },
        {
            "text": "Wait, what?",
            "start": 123.123,
            "duration": 1.134
        },
        {
            "text": "These chairs each\nhave two remotes.",
            "start": 124.257,
            "duration": 2.11
        },
        {
            "text": "Two remotes!",
            "start": 126.392,
            "duration": 0.653
        },
        {
            "text": "On top of the movie theater,\nthere's also an arcade.",
            "start": 127.07,
            "duration": 2.284
        },
        {
            "text": "I was not expecting\nall these features for $1 million.",
            "start": 130.263,
            "duration": 2.669
        },
        {
            "text": "This house is awesome.",
            "start": 133.099,
            "duration": 1.035
        },
        {
            "text": "I'd have so much more friends.",
            "start": 134.134,
            "duration": 1.101
        },
        {
            "text": "If I owned a place like this",
            "start": 135.235,
            "duration": 1.101
        },
        {
            "text": "and ending with the pool,\nwhich comes complete",
            "start": 136.336,
            "duration": 2.469
        },
        {
            "text": "with this unnecessary waterfall.",
            "start": 138.805,
            "duration": 1.902
        },
        {
            "text": "Overall, I'd say this is a\npretty fun house to live in.",
            "start": 140.707,
            "duration": 2.469
        },
        {
            "text": "But of course we're all here\nto see the richest of the rich.",
            "start": 143.176,
            "duration": 2.836
        },
        {
            "text": "And that's why up next,\nwe have these $15 million...",
            "start": 146.187,
            "duration": 4.471
        },
        {
            "text": "$15 million house.",
            "start": 152.289,
            "duration": 1.464
        },
        {
            "text": "Wait, you pushed it?",
            "start": 154.031,
            "duration": 0.59
        },
        {
            "text": "Oh, my God.",
            "start": 154.654,
            "duration": 1.468
        },
        {
            "text": "Jeez, man...",
            "start": 156.122,
            "duration": 1.515
        },
        {
            "text": "I don't belong here.",
            "start": 158.414,
            "duration": 1.112
        },
        {
            "text": "This looks like the house\nthat you tried to get to in GTA.",
            "start": 159.692,
            "duration": 2.703
        },
        {
            "text": "That view is crazy.",
            "start": 162.729,
            "duration": 2.102
        },
        {
            "text": "The pool is much smaller\nthan the $1 million house,",
            "start": 164.831,
            "duration": 2.736
        },
        {
            "text": "but you can literally oversee\nall of L.A.",
            "start": 167.7,
            "duration": 2.503
        },
        {
            "text": "Help!",
            "start": 170.946,
            "duration": 1.006
        },
        {
            "text": "Hey! Help!",
            "start": 172.172,
            "duration": 1.085
        },
        {
            "text": "Stop. Stop.",
            "start": 173.32,
            "duration": 0.83
        },
        {
            "text": "Go inside.",
            "start": 174.174,
            "duration": 0.867
        },
        {
            "text": "I need new friends.",
            "start": 175.041,
            "duration": 1.068
        },
        {
            "text": "Let's check out the house.\nThe person who owns this house.",
            "start": 176.109,
            "duration": 2.602
        },
        {
            "text": "What do you think\nhe does for a living?",
            "start": 178.711,
            "duration": 2.236
        },
        {
            "text": "NFTs",
            "start": 180.947,
            "duration": 1.008
        },
        {
            "text": "He's a lawyer.",
            "start": 181.979,
            "duration": 0.703
        },
        {
            "text": "This guy was the top attorney in 2017\nand the number one lawyer in 2021.",
            "start": 182.682,
            "duration": 4.505
        },
        {
            "text": "Apparently, that's all\nit takes to afford this house.",
            "start": 187.187,
            "duration": 2.068
        },
        {
            "text": "It appears a note was left for us.",
            "start": 189.255,
            "duration": 2.336
        },
        {
            "text": "Dear MrBeast, thank\nyou for visiting my home.",
            "start": 191.791,
            "duration": 2.703
        },
        {
            "text": "You have given me the ultimate gift.",
            "start": 194.736,
            "duration": 1.802
        },
        {
            "text": "I have a trump card with my kids\nforever.",
            "start": 196.563,
            "duration": 2.535
        },
        {
            "text": "Also, please don't eat\nany of the sandwiches.",
            "start": 199.098,
            "duration": 2.136
        },
        {
            "text": "They are very sacred to me",
            "start": 201.234,
            "duration": 1.134
        },
        {
            "text": "and my family's been passing it down\nfrom generation to generation.",
            "start": 202.368,
            "duration": 3.103
        },
        {
            "text": "Got it.",
            "start": 206.539,
            "duration": 0.701
        },
        {
            "text": "- Down or up?\n- Down.",
            "start": 207.24,
            "duration": 0.997
        },
        {
            "text": "Down it is.",
            "start": 208.261,
            "duration": 0.961
        },
        {
            "text": "Okay, now it's starting to look nice.",
            "start": 209.247,
            "duration": 1.763
        },
        {
            "text": "The lower floor of this mansion",
            "start": 211.01,
            "duration": 1.409
        },
        {
            "text": "comes with its very own movie\ntheater and personal gym.",
            "start": 212.444,
            "duration": 2.771
        },
        {
            "text": "This treadmill requires a passcode\nto use.",
            "start": 215.248,
            "duration": 2.436
        },
        {
            "text": "Six, nine, six, nine.",
            "start": 217.742,
            "duration": 1.357
        },
        {
            "text": "It's not six, nine, six, nine.",
            "start": 219.282,
            "duration": 1.405
        },
        {
            "text": "A guest bedroom, an entertainment\narea and a bar where the owner left us",
            "start": 220.687,
            "duration": 3.803
        },
        {
            "text": "a bunch of free food.",
            "start": 224.49,
            "duration": 1.102
        },
        {
            "text": "- Guys, before you eat anything.\n- Yeah.",
            "start": 225.592,
            "duration": 1.968
        },
        {
            "text": "What if he left this out \nso he could sue us for eating his...",
            "start": 227.56,
            "duration": 3.133
        },
        {
            "text": "Well, too late now, Karl ate it.",
            "start": 231.083,
            "duration": 1.1
        },
        {
            "text": "And an incredible underground\nview of the swimming pool.",
            "start": 232.208,
            "duration": 2.993
        },
        {
            "text": "Yeah.",
            "start": 236.402,
            "duration": 1.101
        },
        {
            "text": "Nolan's trying to swim\nin the background for the shot.",
            "start": 239.973,
            "duration": 2.369
        },
        {
            "text": "I don't think he realized\nwe stopped filming him.",
            "start": 242.675,
            "duration": 1.728
        },
        {
            "text": "Back again?",
            "start": 244.428,
            "duration": 0.825
        },
        {
            "text": "Yeah, do it one more time.",
            "start": 245.278,
            "duration": 1.335
        },
        {
            "text": "And now a master bedroom\nwith another crazy view.",
            "start": 246.613,
            "duration": 4.264
        },
        {
            "text": "Karl, come here.",
            "start": 250.95,
            "duration": 1.02
        },
        {
            "text": "You missed.",
            "start": 253.519,
            "duration": 0.835
        },
        {
            "text": "We got another one.",
            "start": 254.354,
            "duration": 1.034
        },
        {
            "text": "You missed again.",
            "start": 255.388,
            "duration": 1.101
        },
        {
            "text": "Oh wait! Nolan, stop it!",
            "start": 256.489,
            "duration": 1.502
        },
        {
            "text": "Nolan, stop this cushion also.",
            "start": 257.991,
            "duration": 1.964
        },
        {
            "text": "Stop throwing cushions.",
            "start": 260.603,
            "duration": 1.759
        },
        {
            "text": "If it goes over the edge he might sue me.",
            "start": 262.395,
            "duration": 1.768
        },
        {
            "text": "And so to avoid being handed court\npapers, we decided to fly all the way",
            "start": 264.163,
            "duration": 3.852
        },
        {
            "text": "across the country to Massachusetts\nfor the $30 million dollar house.",
            "start": 268.04,
            "duration": 4.407
        },
        {
            "text": "This extraordinary 16 bedroom\nestate has four different buildings.",
            "start": 273.906,
            "duration": 4.372
        },
        {
            "text": "In the main house.",
            "start": 279.846,
            "duration": 0.867
        },
        {
            "text": "There are multiple living rooms,\nbut this one is the best",
            "start": 280.713,
            "duration": 3.103
        },
        {
            "text": "of the living rooms in this property.",
            "start": 283.816,
            "duration": 1.936
        },
        {
            "text": "This is grand.",
            "start": 285.752,
            "duration": 1.334
        },
        {
            "text": "- What is this?\n- The Oval Office.",
            "start": 287.086,
            "duration": 2.002
        },
        {
            "text": "What book would you expect here",
            "start": 289.122,
            "duration": 1.368
        },
        {
            "text": "besides The Way To Wealth by Benjamin\nFranklin",
            "start": 290.515,
            "duration": 2.755
        },
        {
            "text": "Bro made the light bulb and a book?",
            "start": 293.403,
            "duration": 1.591
        },
        {
            "text": "Well, Edison made the light bulb.\nNot Ben Franklin.",
            "start": 295.019,
            "duration": 2.102
        },
        {
            "text": "What the hell did\nBen Franklin do?",
            "start": 297.155,
            "duration": 1.426
        },
        {
            "text": "I'm going to read this book.",
            "start": 298.614,
            "duration": 1.39
        },
        {
            "text": "Past the living room in the office",
            "start": 301.082,
            "duration": 1.32
        },
        {
            "text": "was the Grand Kitchen where\nthe owner had left a little gift for us.",
            "start": 302.402,
            "duration": 3.273
        },
        {
            "text": "The owner of this place.\ngot rich making candles.",
            "start": 305.7,
            "duration": 2.14
        },
        {
            "text": "So he made us\ncustom MrBeast candles.",
            "start": 307.84,
            "duration": 2.27
        },
        {
            "text": "That one smells like the beach.",
            "start": 310.134,
            "duration": 1.137
        },
        {
            "text": "It does.",
            "start": 311.311,
            "duration": 0.633
        },
        {
            "text": "How do they put the beach in a candle?",
            "start": 311.944,
            "duration": 1.469
        },
        {
            "text": "And to top off the house's\nmain building,",
            "start": 313.413,
            "duration": 1.935
        },
        {
            "text": "Chandler discovered that...",
            "start": 315.348,
            "duration": 1.376
        },
        {
            "text": "You can hit golf\nballs off the roof.",
            "start": 316.748,
            "duration": 1.558
        },
        {
            "text": "Fore!",
            "start": 319.814,
            "duration": 0.929
        },
        {
            "text": "That's not even close to\nthe coolest thing about this place,",
            "start": 320.768,
            "duration": 2.56
        },
        {
            "text": "because next door\nis a garage filled with exotic cars.",
            "start": 323.353,
            "duration": 3.473
        },
        {
            "text": "This looks like a garage\nout of a video game.",
            "start": 326.826,
            "duration": 2.269
        },
        {
            "text": "They got Lamborghinis\non top of Lamborghinis.",
            "start": 329.128,
            "duration": 2.736
        },
        {
            "text": "It's like a candy store for adults.",
            "start": 331.931,
            "duration": 2.035
        },
        {
            "text": "The best part is\nthis is just one of two car garages.",
            "start": 333.966,
            "duration": 2.737
        },
        {
            "text": "- Follow me.\n- There's more?",
            "start": 336.703,
            "duration": 1.095
        },
        {
            "text": "Bro, there's more cars in here\nthan the other one.",
            "start": 337.829,
            "duration": 2.01
        },
        {
            "text": "Holy crap!",
            "start": 340.032,
            "duration": 1.409
        },
        {
            "text": "All right, now I am convinced if\nwe steal a car, he would not notice.",
            "start": 341.441,
            "duration": 3.036
        },
        {
            "text": "How do you even buy these cars?\nHey, I want three of the same ones.",
            "start": 344.477,
            "duration": 2.536
        },
        {
            "text": "It's like a full time job\nto buy this many cars.",
            "start": 347.013,
            "duration": 2.402
        },
        {
            "text": "There's stairs in the corner.\nLet's see where they go.",
            "start": 349.415,
            "duration": 2.321
        },
        {
            "text": "Bro, this is like a\ncloset with cars.",
            "start": 351.761,
            "duration": 2.293
        },
        {
            "text": "Underneath the car garage\nis another army of cars.",
            "start": 354.079,
            "duration": 3.144
        },
        {
            "text": "They should really invest in a light\nswitch down here.",
            "start": 357.29,
            "duration": 2.002
        },
        {
            "text": "They have 20 cars down here,\nbut no lights.",
            "start": 359.292,
            "duration": 2.002
        },
        {
            "text": "- Did I...?\n- No way!",
            "start": 363.289,
            "duration": 1.517
        },
        {
            "text": "No.",
            "start": 364.831,
            "duration": 0.967
        },
        {
            "text": "No way!",
            "start": 367.22,
            "duration": 1.531
        },
        {
            "text": "That's\nwhy there wasn't a light switch.",
            "start": 371.371,
            "duration": 1.634
        },
        {
            "text": "I was like,\nwho can afford to shove 30 cars",
            "start": 373.005,
            "duration": 2.002
        },
        {
            "text": "in their basement\nbut not electricity?",
            "start": 375.007,
            "duration": 1.802
        },
        {
            "text": "Now, don't get me wrong,\nall of the rooms",
            "start": 376.809,
            "duration": 1.669
        },
        {
            "text": "in this house\nhave been awesome so far.",
            "start": 378.478,
            "duration": 1.902
        },
        {
            "text": "But if I owned it, I don't think\nI'd ever leave this next building.",
            "start": 380.38,
            "duration": 3.403
        },
        {
            "text": "This is awesome.",
            "start": 383.85,
            "duration": 1.801
        },
        {
            "text": "That's right.",
            "start": 385.651,
            "duration": 0.601
        },
        {
            "text": "For some just ungodly reason,\nwhoever built this place thought",
            "start": 386.252,
            "duration": 3.47
        },
        {
            "text": "it would be a good idea to install an\nentire indoor tennis court.",
            "start": 389.722,
            "duration": 3.637
        },
        {
            "text": "I just want to remind you that\nwe are playing tennis inside a house.",
            "start": 393.784,
            "duration": 3.497
        },
        {
            "text": "I also have no idea how to play\ntennis.",
            "start": 399.832,
            "duration": 1.569
        },
        {
            "text": "Gang squad, follow me.",
            "start": 401.401,
            "duration": 1.436
        },
        {
            "text": "What?\nNo way!",
            "start": 402.947,
            "duration": 1.933
        },
        {
            "text": "Two story arcade.",
            "start": 404.904,
            "duration": 1.134
        },
        {
            "text": "The arcade in this house",
            "start": 406.038,
            "duration": 1.068
        },
        {
            "text": "is actually 20 times bigger\nthan the one at the $1 million house.",
            "start": 407.106,
            "duration": 3.537
        },
        {
            "text": "But that's not all.",
            "start": 410.668,
            "duration": 0.868
        },
        {
            "text": "Bro, this place literally has everything.",
            "start": 413.012,
            "duration": 1.902
        },
        {
            "text": "All right, I'm never leaving.",
            "start": 414.914,
            "duration": 1.301
        },
        {
            "text": "We're playing ping pong\nin a basketball court, in a house.",
            "start": 416.215,
            "duration": 3.481
        },
        {
            "text": "First try, baby!",
            "start": 421.387,
            "duration": 1.201
        },
        {
            "text": "Now, all of the features of the $30\nmillion house have been pretty cool.",
            "start": 422.588,
            "duration": 3.504
        },
        {
            "text": "But this next room is\nwhat makes this place truly special.",
            "start": 426.092,
            "duration": 3.236
        },
        {
            "text": "Head up these stairs\nfor the best part of the estate.",
            "start": 429.328,
            "duration": 2.87
        },
        {
            "text": "What you really want to see is\nright over here, look at this.",
            "start": 432.265,
            "duration": 4.088
        },
        {
            "text": "This is an indoor waterpark.",
            "start": 436.394,
            "duration": 2.537
        },
        {
            "text": "It's like a whole new world in here.",
            "start": 440.373,
            "duration": 1.701
        },
        {
            "text": "Look how far back the drone is\nand it's still going.",
            "start": 442.074,
            "duration": 3.17
        },
        {
            "text": "Go have fun,\nbut don't break anything.",
            "start": 445.244,
            "duration": 2.336
        },
        {
            "text": "Roger that.",
            "start": 447.806,
            "duration": 1.007
        },
        {
            "text": "We're all about to go down\nthe slide together.",
            "start": 454.29,
            "duration": 2.248
        },
        {
            "text": "We're going to enjoy the waterpark.",
            "start": 462.128,
            "duration": 1.435
        },
        {
            "text": "I'll see you at the next house.",
            "start": 463.563,
            "duration": 1.368
        },
        {
            "text": "The only bad news is it's once again\nacross the entire country.",
            "start": 464.931,
            "duration": 3.803
        },
        {
            "text": "The good news is it's a $45\nmillion mega-mansion.",
            "start": 469.009,
            "duration": 4.071
        },
        {
            "text": "- What!\n- Oh, my gosh.",
            "start": 474.098,
            "duration": 1.71
        },
        {
            "text": "This is like the most open house\nI've ever been in.",
            "start": 475.833,
            "duration": 1.859
        },
        {
            "text": "What?",
            "start": 477.731,
            "duration": 0.589
        },
        {
            "text": "I don't know what majestic thing\nthis is, but it's beautiful.",
            "start": 478.344,
            "duration": 3.237
        },
        {
            "text": "As you can probably tell,",
            "start": 481.581,
            "duration": 1.268
        },
        {
            "text": "these houses\nare starting to get so expensive,",
            "start": 482.849,
            "duration": 2.068
        },
        {
            "text": "I don't even know how\nto describe them anymore.",
            "start": 484.917,
            "duration": 1.829
        },
        {
            "text": "Honestly, lost for words.",
            "start": 486.771,
            "duration": 1.583
        },
        {
            "text": "This is quite possibly the most\nbeautiful thing I've ever seen.",
            "start": 488.354,
            "duration": 2.936
        },
        {
            "text": "So I called in multi-billionaire\nMark Cuban to help us out.",
            "start": 491.29,
            "duration": 3.345
        },
        {
            "text": "- How's it going?\n- Hey!",
            "start": 494.66,
            "duration": 1.21
        },
        {
            "text": "- How's it going, little man?\n- Nice to meet you.",
            "start": 496.285,
            "duration": 1.171
        },
        {
            "text": "Mark's also the proud owner of\nthe Dallas Mavericks basketball team.",
            "start": 497.481,
            "duration": 3.185
        },
        {
            "text": "And because this house\nhas its very own basketball court,",
            "start": 500.666,
            "duration": 2.77
        },
        {
            "text": "you can imagine\nwe got a little distracted.",
            "start": 503.469,
            "duration": 2.069
        },
        {
            "text": "- Jimmy won't make it!\n- Buckets!",
            "start": 506.028,
            "duration": 1.367
        },
        {
            "text": "Just steal it from Karl.",
            "start": 508.407,
            "duration": 1.469
        },
        {
            "text": "Hit that.",
            "start": 509.876,
            "duration": 0.5
        },
        {
            "text": "- No shot.\n- We get those.",
            "start": 510.376,
            "duration": 1.613
        },
        {
            "text": "Yeah, that's it.",
            "start": 512.145,
            "duration": 0.867
        },
        {
            "text": "Go, go, go, go, go.\nEasy lay bud",
            "start": 513.037,
            "duration": 1.804
        },
        {
            "text": "Yeah.",
            "start": 514.996,
            "duration": 1.061
        },
        {
            "text": "There we go. Jake's play wins.\nAll you. Hit it. Game winner.",
            "start": 516.082,
            "duration": 2.769
        },
        {
            "text": "Oh, no.",
            "start": 518.885,
            "duration": 0.542
        },
        {
            "text": "Yeah!",
            "start": 519.458,
            "duration": 1.029
        },
        {
            "text": "Way to dominate, Jakers.",
            "start": 520.52,
            "duration": 1.298
        },
        {
            "text": "Now, we're going to show Mark\naround the rest of the house,",
            "start": 521.843,
            "duration": 1.613
        },
        {
            "text": "Now that we're all sweating.",
            "start": 523.456,
            "duration": 1.107
        },
        {
            "text": "To find out if he thought it was worth\nthe steep $45 million price.",
            "start": 524.588,
            "duration": 4.073
        },
        {
            "text": "In case you're wondering,\nwe didn't go swimming.",
            "start": 528.661,
            "duration": 2.002
        },
        {
            "text": "It looks like I did go swimming.",
            "start": 530.663,
            "duration": 1.802
        },
        {
            "text": "- How much do they want for this house?\n- 45.",
            "start": 532.465,
            "duration": 2.267
        },
        {
            "text": "- Not worth it?\n- Because it's Brentwood.",
            "start": 535.434,
            "duration": 2.002
        },
        {
            "text": "That's probably half of it.",
            "start": 537.436,
            "duration": 1.335
        },
        {
            "text": "Is Brentwood what that is?",
            "start": 538.771,
            "duration": 1.188
        },
        {
            "text": "No, the neighborhood.",
            "start": 540.13,
            "duration": 1.878
        },
        {
            "text": "I also thought he was talking\nabout the wood in the house.",
            "start": 542.659,
            "duration": 2.253
        },
        {
            "text": "That's funny.",
            "start": 545.444,
            "duration": 0.768
        },
        {
            "text": "This bathroom over here, it's nice.",
            "start": 546.212,
            "duration": 1.635
        },
        {
            "text": "Do you have a couch in your bathroom?",
            "start": 547.847,
            "duration": 1.968
        },
        {
            "text": "- Yes.\n- Oh really?",
            "start": 549.815,
            "duration": 1.569
        },
        {
            "text": "Yeah.",
            "start": 551.384,
            "duration": 0.534
        },
        {
            "text": "Okay. We need to get on Mark's level.",
            "start": 551.918,
            "duration": 1.148
        },
        {
            "text": "The number one rule is, you have to\nhave a heated seat.",
            "start": 553.091,
            "duration": 3.079
        },
        {
            "text": "That's it?",
            "start": 556.195,
            "duration": 0.37
        },
        {
            "text": "- That feeling when you sit down...\n- And it is not cold?",
            "start": 556.589,
            "duration": 2.469
        },
        {
            "text": "I agree.",
            "start": 559.759,
            "duration": 0.6
        },
        {
            "text": "You don't need to make billions\nto be happy.",
            "start": 560.359,
            "duration": 1.702
        },
        {
            "text": "You just need to be able to afford\na bidet and a heated toilet seat.",
            "start": 562.093,
            "duration": 2.903
        },
        {
            "text": "Cause that's where I spend\nmost of my time.",
            "start": 565.031,
            "duration": 1.835
        },
        {
            "text": "Well, even though I'm sure Mark\nwould love to spend more time",
            "start": 566.866,
            "duration": 2.235
        },
        {
            "text": "here on the toilets,\nour time here is officially ran out.",
            "start": 569.101,
            "duration": 2.903
        },
        {
            "text": "And so I'll see you guys\nat the next house.",
            "start": 572.004,
            "duration": 2.503
        },
        {
            "text": "Up next, we have a house\nwhose price point happens",
            "start": 574.907,
            "duration": 2.369
        },
        {
            "text": "to be my favorite number.",
            "start": 577.276,
            "duration": 1.468
        },
        {
            "text": "And now we are at the $69 million\nmansion.",
            "start": 578.744,
            "duration": 3.504
        },
        {
            "text": "That looks like a villain owns it.",
            "start": 582.381,
            "duration": 1.82
        },
        {
            "text": "It does look villainous.",
            "start": 584.232,
            "duration": 1.386
        },
        {
            "text": "How's this compare to your house, Miranda?",
            "start": 585.618,
            "duration": 1.902
        },
        {
            "text": "It's a lot bigger than mine.",
            "start": 587.52,
            "duration": 1.868
        },
        {
            "text": "That can't be sure.\nWhat's your address?",
            "start": 589.388,
            "duration": 2.269
        },
        {
            "text": "The reason why this weird looking\nhouse can still go on the market",
            "start": 592.084,
            "duration": 2.61
        },
        {
            "text": "for $69 million\nis because it's filled to the brim",
            "start": 594.694,
            "duration": 3.203
        },
        {
            "text": "with priceless art and sculptures\nsourced from all around the world.",
            "start": 597.897,
            "duration": 3.77
        },
        {
            "text": "Throw up\nhow much these artworks are worth",
            "start": 601.701,
            "duration": 1.968
        },
        {
            "text": "and we're going to try to guess it.\nHow much do you think this is worth?",
            "start": 603.669,
            "duration": 2.436
        },
        {
            "text": "I'm going to say 100,000.",
            "start": 607.907,
            "duration": 1.301
        },
        {
            "text": "- What do you think, Miranda?\n- I'm going to go with 80.",
            "start": 609.208,
            "duration": 1.668
        },
        {
            "text": "Oh, she has one of these in her house.",
            "start": 610.876,
            "duration": 1.602
        },
        {
            "text": "Yeah. I have the same one.",
            "start": 612.478,
            "duration": 1.368
        },
        {
            "text": "Only you know the actual price.",
            "start": 613.87,
            "duration": 1.544
        },
        {
            "text": "Oh, actually,\nthis one will be a fun one.",
            "start": 615.448,
            "duration": 1.835
        },
        {
            "text": "I'm going to go with $1,000,000\nbecause it's like right down",
            "start": 617.283,
            "duration": 2.469
        },
        {
            "text": "the opening stairs, so...",
            "start": 619.752,
            "duration": 1.385
        },
        {
            "text": "$450,000",
            "start": 621.162,
            "duration": 1.148
        },
        {
            "text": "- Very precise.\n- Very specific.",
            "start": 622.342,
            "duration": 1.882
        },
        {
            "text": "The $30 million house",
            "start": 624.256,
            "duration": 1.202
        },
        {
            "text": "had a waterpark, a hundred cars.",
            "start": 625.558,
            "duration": 2.135
        },
        {
            "text": "This place just has artwork.",
            "start": 627.693,
            "duration": 2.43
        },
        {
            "text": "Big red sculpture.",
            "start": 630.194,
            "duration": 1.246
        },
        {
            "text": "This room over here,\nwe promised them 30 times",
            "start": 631.464,
            "duration": 2.769
        },
        {
            "text": "we wouldn't touch what's in it.",
            "start": 634.258,
            "duration": 1.052
        },
        {
            "text": "Come over here.",
            "start": 635.342,
            "duration": 0.535
        },
        {
            "text": "No touching anything, what is it?",
            "start": 635.901,
            "duration": 2.403
        },
        {
            "text": "This is a one of one\nfully analog custom home sound system",
            "start": 638.671,
            "duration": 4.137
        },
        {
            "text": "made by the creator of the Walkman,\nwhich was one of the first devices",
            "start": 642.842,
            "duration": 3.603
        },
        {
            "text": "that allowed you to listen to music\nwhile walking.",
            "start": 646.445,
            "duration": 2.002
        },
        {
            "text": "That's an impressive thing\nto have under your belt.",
            "start": 648.447,
            "duration": 1.902
        },
        {
            "text": "To have made the Walkman.",
            "start": 650.349,
            "duration": 1.635
        },
        {
            "text": "I don't think you could fit this\nunder your belt.",
            "start": 651.984,
            "duration": 1.576
        },
        {
            "text": "Let's traverse across the skywalk.",
            "start": 655.826,
            "duration": 1.263
        },
        {
            "text": "Oh, my God. I'm excited.",
            "start": 657.39,
            "duration": 0.667
        },
        {
            "text": "Another reason\nthis house is built so strange.",
            "start": 658.057,
            "duration": 2.603
        },
        {
            "text": "For example, having to walk across\nSkyBridge is to get anywhere",
            "start": 660.66,
            "duration": 3.37
        },
        {
            "text": "is because it's\nbeen meticulously built",
            "start": 664.03,
            "duration": 2.002
        },
        {
            "text": "to be able to withstand\nthe force of a real tsunami.",
            "start": 666.132,
            "duration": 3.169
        },
        {
            "text": "I mean, you got to admit,\nthat's pretty cool.",
            "start": 669.568,
            "duration": 2.0
        },
        {
            "text": "You can see the tsunamis before\nthey hit your house and you stop them.",
            "start": 671.929,
            "duration": 2.858
        },
        {
            "text": "What completes\nthe view is the neighbor's backyard.",
            "start": 675.241,
            "duration": 3.37
        },
        {
            "text": "You can see all of it.",
            "start": 678.611,
            "duration": 1.234
        },
        {
            "text": "What if the man who lives here\nis secretly in love",
            "start": 679.845,
            "duration": 2.211
        },
        {
            "text": "with the person that lives next door?",
            "start": 682.088,
            "duration": 1.644
        },
        {
            "text": "That's his ex girlfriend.",
            "start": 683.757,
            "duration": 1.367
        },
        {
            "text": "It's a Romeo and Juliet.",
            "start": 685.279,
            "duration": 1.081
        },
        {
            "text": "And after checking out\nthe last two rooms inside,",
            "start": 686.385,
            "duration": 2.469
        },
        {
            "text": "I had a surprise\nwaiting for us outside.",
            "start": 688.854,
            "duration": 1.936
        },
        {
            "text": "Look over there.",
            "start": 690.79,
            "duration": 0.774
        },
        {
            "text": "What?",
            "start": 692.013,
            "duration": 0.641
        },
        {
            "text": "Deez nuts.",
            "start": 692.678,
            "duration": 1.491
        },
        {
            "text": "Did you guys even notice\nthe planes drawing that?",
            "start": 694.193,
            "duration": 1.635
        },
        {
            "text": "No.",
            "start": 695.828,
            "duration": 1.134
        },
        {
            "text": "How on earth did they do that?",
            "start": 696.962,
            "duration": 1.394
        },
        {
            "text": "I paid these planes\nand also about a thousand billboards",
            "start": 698.381,
            "duration": 2.619
        },
        {
            "text": "all across America\nto let everyone know",
            "start": 701.0,
            "duration": 1.668
        },
        {
            "text": "that Feastables is the best\ntasting chocolate you can buy.",
            "start": 702.693,
            "duration": 2.469
        },
        {
            "text": "Stop eating Hershey's and other boomer\nbrand's, Feastables is modern chocolate.",
            "start": 705.204,
            "duration": 3.637
        },
        {
            "text": "Also, because halloween is coming up\nin all these retailers",
            "start": 708.841,
            "duration": 2.236
        },
        {
            "text": "you see here, we're now",
            "start": 711.077,
            "duration": 1.001
        },
        {
            "text": "selling these bags\nof these smaller pieces bars",
            "start": 712.078,
            "duration": 2.335
        },
        {
            "text": "so you can give them out during trick\nor treating.",
            "start": 714.413,
            "duration": 1.669
        },
        {
            "text": "If you don't want to be lame\non Halloween,",
            "start": 716.082,
            "duration": 1.668
        },
        {
            "text": "make sure you give away\nFeastables to trick-or-treaters.",
            "start": 717.75,
            "duration": 2.002
        },
        {
            "text": "Luckily,\nour candy is pretty affordable,",
            "start": 719.922,
            "duration": 1.965
        },
        {
            "text": "but you know what's not so affordable?",
            "start": 721.996,
            "duration": 1.702
        },
        {
            "text": "The final house,\nor should I say",
            "start": 723.723,
            "duration": 2.761
        },
        {
            "text": "the $139 million",
            "start": 726.509,
            "duration": 3.9
        },
        {
            "text": "arguably most luxurious house on the\nplanet Mega-Mansion",
            "start": 730.433,
            "duration": 3.533
        },
        {
            "text": "This massive",
            "start": 735.501,
            "duration": 1.001
        },
        {
            "text": "36,000 square foot mansion has things\nyou never see in any other house,",
            "start": 736.502,
            "duration": 4.805
        },
        {
            "text": "from a nightclub to a T-Rex\nto an entire robotic car elevator.",
            "start": 741.44,
            "duration": 4.972
        },
        {
            "text": "This place is going to blow your mind\nand to make this house tour",
            "start": 746.412,
            "duration": 3.91
        },
        {
            "text": "extra special,\nwe brought Justin Timberlake.",
            "start": 750.347,
            "duration": 2.238
        },
        {
            "text": "How you guys doing?",
            "start": 752.718,
            "duration": 0.868
        },
        {
            "text": "And this is Justin's house\nand he's going to show us around.",
            "start": 753.611,
            "duration": 2.969
        },
        {
            "text": "No.",
            "start": 756.828,
            "duration": 0.781
        },
        {
            "text": "Holy crap!",
            "start": 758.016,
            "duration": 1.051
        },
        {
            "text": "Have you ever seen a view\nbetter than this in your life?",
            "start": 759.091,
            "duration": 1.969
        },
        {
            "text": "- This is gorgeous.\n- Yeah, man, you guys really...",
            "start": 761.06,
            "duration": 2.736
        },
        {
            "text": "The CGI is perfect, it looks real.",
            "start": 763.821,
            "duration": 2.25
        },
        {
            "text": "He's like, \"Yeah, maybe it's top 10.\"",
            "start": 767.333,
            "duration": 1.701
        },
        {
            "text": "I'll put it top five.",
            "start": 769.034,
            "duration": 1.368
        },
        {
            "text": "It's hard to describe\njust how big this mansion really is.",
            "start": 770.402,
            "duration": 3.637
        },
        {
            "text": "It has 12 bedrooms and 17 bathrooms\nsplit across three massive",
            "start": 774.106,
            "duration": 4.772
        },
        {
            "text": "stories, all with a perfect view\nof the Los Angeles skyline.",
            "start": 778.878,
            "duration": 3.47
        },
        {
            "text": "I always judge a house\nby the kitchen, minimalist kitchen.",
            "start": 782.481,
            "duration": 3.27
        },
        {
            "text": "You judge these things.\nHow are you feeling?",
            "start": 785.953,
            "duration": 1.625
        },
        {
            "text": "Well, let's keep going.",
            "start": 788.12,
            "duration": 1.001
        },
        {
            "text": "At the end of the tour,\nwe'll get his opinion on",
            "start": 789.121,
            "duration": 2.236
        },
        {
            "text": "if he would pay $100 million.",
            "start": 791.357,
            "duration": 1.501
        },
        {
            "text": "He has it on standby if he likes it.",
            "start": 792.858,
            "duration": 2.169
        },
        {
            "text": "Straight cash, homie.",
            "start": 795.06,
            "duration": 1.302
        },
        {
            "text": "Everything in this house is built\nout of the most expensive materials",
            "start": 796.362,
            "duration": 3.67
        },
        {
            "text": "on the planet.",
            "start": 800.032,
            "duration": 0.601
        },
        {
            "text": "For example, the walls in this room\nare constructed entirely out of rare",
            "start": 800.633,
            "duration": 3.937
        },
        {
            "text": "marble, imported straight from Italy.",
            "start": 804.57,
            "duration": 2.102
        },
        {
            "text": "You guys got to get an estimate\nor something",
            "start": 806.672,
            "duration": 1.935
        },
        {
            "text": "on how much marble\nis actually in this house.",
            "start": 808.607,
            "duration": 2.403
        },
        {
            "text": "I mean, that's a\nthat's like custom done.",
            "start": 811.01,
            "duration": 2.327
        },
        {
            "text": "Yeah, there's not a single thing\nof drywall in this entire house.",
            "start": 813.416,
            "duration": 2.499
        },
        {
            "text": "Drywall?",
            "start": 815.915,
            "duration": 1.164
        },
        {
            "text": "This is a pretty sick chandelier.",
            "start": 817.83,
            "duration": 1.263
        },
        {
            "text": "This chandelier is over $1,000,000.",
            "start": 819.118,
            "duration": 2.269
        },
        {
            "text": "And the ceiling\nliterally started dipping",
            "start": 821.387,
            "duration": 2.169
        },
        {
            "text": "because it weighs\nso many thousands of pounds.",
            "start": 823.556,
            "duration": 1.768
        },
        {
            "text": "It really keeps going.",
            "start": 825.324,
            "duration": 1.235
        },
        {
            "text": "You didn't tell me it was a million.\nI was playing with it earlier.",
            "start": 826.559,
            "duration": 2.435
        },
        {
            "text": "There is literally $6 million\nof just chandeliers in this house",
            "start": 828.994,
            "duration": 4.672
        },
        {
            "text": "and the rooms on the bottom floor\nget even better.",
            "start": 833.666,
            "duration": 2.498
        },
        {
            "text": "There's a whole other house\ndown here.",
            "start": 836.189,
            "duration": 1.71
        },
        {
            "text": "If you come over here...",
            "start": 837.924,
            "duration": 1.289
        },
        {
            "text": "Dude, this is literally an ice room.",
            "start": 839.238,
            "duration": 1.702
        },
        {
            "text": "- This is where you lock me in?\n- No.",
            "start": 840.94,
            "duration": 1.902
        },
        {
            "text": "Please don't.",
            "start": 842.842,
            "duration": 0.951
        },
        {
            "text": "So, what do you do in here?",
            "start": 844.81,
            "duration": 1.714
        },
        {
            "text": "They ran out of room ideas.",
            "start": 849.748,
            "duration": 1.502
        },
        {
            "text": "Probably a 50%\nchance we're locked in here",
            "start": 851.25,
            "duration": 2.569
        },
        {
            "text": "because that doesn't have a handle.",
            "start": 853.844,
            "duration": 1.151
        },
        {
            "text": "Oh, no. We're good.",
            "start": 855.002,
            "duration": 0.803
        },
        {
            "text": "That would have been funny if we were",
            "start": 855.83,
            "duration": 1.312
        },
        {
            "text": "His face.",
            "start": 857.173,
            "duration": 1.062
        },
        {
            "text": "Is that a real dinosaur?",
            "start": 861.026,
            "duration": 1.068
        },
        {
            "text": "Now that you know the house has a\ndinosaur, are you more apt to buy it?",
            "start": 862.094,
            "duration": 3.579
        },
        {
            "text": "I'm still on the fence.",
            "start": 866.665,
            "duration": 1.054
        },
        {
            "text": "What?",
            "start": 869.125,
            "duration": 0.89
        },
        {
            "text": "Is this a locker room?",
            "start": 870.04,
            "duration": 1.039
        },
        {
            "text": "No one currently owns this house,",
            "start": 871.118,
            "duration": 1.854
        },
        {
            "text": "so they put nametags\nof the few people",
            "start": 872.972,
            "duration": 2.068
        },
        {
            "text": "on the planet\nthat can actually afford it.",
            "start": 875.04,
            "duration": 1.874
        },
        {
            "text": "Warren Buffett's worth like 80 billion,\nEllison's worth, like 50 billion.",
            "start": 876.946,
            "duration": 3.133
        },
        {
            "text": "Bezos Like 100 billion.",
            "start": 880.079,
            "duration": 1.434
        },
        {
            "text": "Chandler, why is your name not up here?",
            "start": 881.513,
            "duration": 1.869
        },
        {
            "text": "All right, let's check out the whips.",
            "start": 885.451,
            "duration": 1.468
        },
        {
            "text": "- Nolan, are you just posing?\n- I'll just be sitting here.",
            "start": 886.919,
            "duration": 2.669
        },
        {
            "text": "You really match the house.",
            "start": 889.622,
            "duration": 1.701
        },
        {
            "text": "Thank you.",
            "start": 891.323,
            "duration": 0.467
        },
        {
            "text": "I was going for that, I was going for that.",
            "start": 891.79,
            "duration": 1.749
        },
        {
            "text": "Job well done.",
            "start": 893.579,
            "duration": 0.823
        },
        {
            "text": "Nolan's going to go in the editing room\nand clip that.",
            "start": 894.426,
            "duration": 2.285
        },
        {
            "text": "This $2.5 million car elevator",
            "start": 897.97,
            "duration": 2.701
        },
        {
            "text": "is one of the most insane\nfeatures in the whole house.",
            "start": 900.696,
            "duration": 2.94
        },
        {
            "text": "You select which car\nyou want to drive on the tablet,",
            "start": 903.636,
            "duration": 2.736
        },
        {
            "text": "and it literally sends it up\ntwo floors right into the garage.",
            "start": 906.372,
            "duration": 3.47
        },
        {
            "text": "I know what you're thinking.",
            "start": 909.842,
            "duration": 0.901
        },
        {
            "text": "The main problem with\nthis is it only stores",
            "start": 910.743,
            "duration": 1.935
        },
        {
            "text": "- Six Lamborghinis and...\n- Yeah...",
            "start": 912.678,
            "duration": 1.643
        },
        {
            "text": "You needed like a ten car storage.",
            "start": 914.454,
            "duration": 2.0
        },
        {
            "text": "Right.",
            "start": 916.548,
            "duration": 0.634
        },
        {
            "text": "This house also had the by far",
            "start": 917.182,
            "duration": 2.036
        },
        {
            "text": "biggest home theater\nI've ever seen in my life.",
            "start": 919.243,
            "duration": 3.181
        },
        {
            "text": "This almost looks\nlike a real movie theater.",
            "start": 923.088,
            "duration": 1.235
        },
        {
            "text": "This is the best movie\ntheater so far.",
            "start": 924.323,
            "duration": 2.436
        },
        {
            "text": "And they're actually reclining\nchairs.",
            "start": 926.792,
            "duration": 1.902
        },
        {
            "text": "It only costs\n100 mil for that.",
            "start": 928.694,
            "duration": 1.947
        },
        {
            "text": "Check it out, Jimmy.\nWait, press my massage button.",
            "start": 930.666,
            "duration": 2.186
        },
        {
            "text": "I got you.",
            "start": 932.865,
            "duration": 0.768
        },
        {
            "text": "Hey! I don't need this",
            "start": 938.454,
            "duration": 1.664
        },
        {
            "text": "Bro, where's my button?\nMy chair's not even doing that.",
            "start": 942.211,
            "duration": 2.405
        },
        {
            "text": "Here, switch. Let me see.",
            "start": 944.649,
            "duration": 0.862
        },
        {
            "text": "Yeah, Chandler test the massage feature.",
            "start": 945.511,
            "duration": 2.044
        },
        {
            "text": "Oh, my god, it works.",
            "start": 949.352,
            "duration": 2.031
        },
        {
            "text": "No way this is just the only one here.",
            "start": 951.383,
            "duration": 2.369
        },
        {
            "text": "Man. This is great.",
            "start": 953.752,
            "duration": 1.877
        },
        {
            "text": "Bro, what is wrong with them?",
            "start": 955.654,
            "duration": 1.531
        },
        {
            "text": "All right, lead the way upstairs.",
            "start": 958.09,
            "duration": 1.802
        },
        {
            "text": "This is a primary bedroom over here.",
            "start": 959.892,
            "duration": 2.293
        },
        {
            "text": "Oh, and then over here.",
            "start": 963.929,
            "duration": 1.201
        },
        {
            "text": "The bathrooms.",
            "start": 965.13,
            "duration": 0.734
        },
        {
            "text": "In case you've ever\nwanted to shower with ten people.",
            "start": 965.864,
            "duration": 2.002
        },
        {
            "text": "Now you can.",
            "start": 968.6,
            "duration": 0.668
        },
        {
            "text": "That's my thing, man.",
            "start": 969.268,
            "duration": 1.301
        },
        {
            "text": "You can take a bath with no one.",
            "start": 970.569,
            "duration": 1.702
        },
        {
            "text": "And basically all yourself\nbut showering.",
            "start": 972.271,
            "duration": 2.269
        },
        {
            "text": "You can fit an army in there.",
            "start": 974.673,
            "duration": 1.368
        },
        {
            "text": "- If that's what you're into.\n- He is.",
            "start": 976.066,
            "duration": 2.119
        },
        {
            "text": "And now the best part of the house\nover at the pool.",
            "start": 979.453,
            "duration": 2.102
        },
        {
            "text": "The real reason this house cost\nso much.",
            "start": 981.58,
            "duration": 2.207
        },
        {
            "text": "I'm pressing it.",
            "start": 983.812,
            "duration": 0.784
        },
        {
            "text": "Is this a screen?",
            "start": 986.529,
            "duration": 1.242
        },
        {
            "text": "It is absurdly large.",
            "start": 987.811,
            "duration": 2.577
        },
        {
            "text": "And slow.",
            "start": 994.593,
            "duration": 0.734
        },
        {
            "text": "- It gives drama, though.\n- It is. Exactly.",
            "start": 995.352,
            "duration": 2.093
        },
        {
            "text": "It gives a dramatic effect.",
            "start": 997.522,
            "duration": 2.031
        },
        {
            "text": "I mean...",
            "start": 1006.605,
            "duration": 0.834
        },
        {
            "text": "It's a little bit of a flex.",
            "start": 1008.173,
            "duration": 1.268
        },
        {
            "text": "What a gorgeous view of L.A.",
            "start": 1009.441,
            "duration": 1.69
        },
        {
            "text": "Yeah. Imagine\nthis screensaver was L.A.",
            "start": 1011.917,
            "duration": 2.002
        },
        {
            "text": "I think it is.",
            "start": 1014.013,
            "duration": 1.167
        },
        {
            "text": "There's downtown L.A.",
            "start": 1015.18,
            "duration": 1.635
        },
        {
            "text": "and there's downtown L.A.",
            "start": 1016.815,
            "duration": 1.802
        },
        {
            "text": "For reference, Karl is\nlike six foot five.",
            "start": 1018.617,
            "duration": 2.202
        },
        {
            "text": "Yeah, something like that.\nGive or take",
            "start": 1020.819,
            "duration": 1.264
        },
        {
            "text": "And look\nhow tall the TV is compared to him.",
            "start": 1022.108,
            "duration": 2.181
        },
        {
            "text": "All right, Justin,\nyou've seen the whole house.",
            "start": 1024.49,
            "duration": 2.602
        },
        {
            "text": "We need to know.",
            "start": 1027.292,
            "duration": 0.835
        },
        {
            "text": "Obviously, you have $100 million\nin cash sitting outside.",
            "start": 1028.152,
            "duration": 3.384
        },
        {
            "text": "Right.",
            "start": 1031.677,
            "duration": 0.563
        },
        {
            "text": "Are you going to buy the house?",
            "start": 1032.264,
            "duration": 1.201
        },
        {
            "text": "- Nolan's shirt comes with it.\n- You don't like my shirt?",
            "start": 1033.465,
            "duration": 1.835
        },
        {
            "text": "- Your shirt comes with it?\n- Yeah.",
            "start": 1035.3,
            "duration": 1.435
        },
        {
            "text": "I'm in. Does the bear that\nripped up the shirt come with it?",
            "start": 1036.735,
            "duration": 3.441
        },
        {
            "text": "Oh, no!",
            "start": 1044.45,
            "duration": 1.161
        },
        {
            "text": "Let's go!",
            "start": 1045.611,
            "duration": 0.634
        },
        {
            "text": "- Wait, wait.\n- Why?",
            "start": 1046.27,
            "duration": 1.406
        },
        {
            "text": "I hope you guys enjoyed it",
            "start": 1047.746,
            "duration": 1.535
        },
        {
            "text": "I'll see you around.",
            "start": 1049.306,
            "duration": 1.006
        }
    ],
    "stats": {
        "viewCount": "223980681",
        "likeCount": "5382477",
        "favoriteCount": "0",
        "commentCount": "136520"
    }
}