{
    "id": "tnTPaLOaHz8",
    "title": "$10,000 Every Day You Survive In A Grocery Store",
    "publishedAt": "2023-12-02T17:00:00Z",
    "captions": [
        {
            "text": "I just\nbought this entire grocery store,",
            "start": 0.0,
            "duration": 3.136
        },
        {
            "text": "which includes enough food\nto literally feed an entire city.",
            "start": 3.136,
            "duration": 4.137
        },
        {
            "text": "And then I decided to trap\nthis random guy inside.",
            "start": 7.307,
            "duration": 3.136
        },
        {
            "text": "And every day you live here, I will\ngive you $10,000 in a grocery cart.",
            "start": 10.443,
            "duration": 4.638
        },
        {
            "text": "That's wild, dude. Let's go.",
            "start": 15.115,
            "duration": 1.868
        },
        {
            "text": "- Well I'll give it to you in 24 hours.\n- Okay.",
            "start": 17.017,
            "duration": 1.768
        },
        {
            "text": "This challenge could literally\nmake Alex a multimillionaire,",
            "start": 18.818,
            "duration": 3.37
        },
        {
            "text": "which in theory means\nhe could be in here for years.",
            "start": 22.222,
            "duration": 2.736
        },
        {
            "text": "And it starts right now.",
            "start": 24.958,
            "duration": 1.601
        },
        {
            "text": "All right, Jimmy's gone.",
            "start": 26.559,
            "duration": 1.068
        },
        {
            "text": "Why would I ever leave?\nI could be here for years.",
            "start": 27.627,
            "duration": 2.436
        },
        {
            "text": "Time to go grocery\nshopping, baby.",
            "start": 30.096,
            "duration": 1.702
        },
        {
            "text": "Now, if Alex crosses this red line,",
            "start": 31.798,
            "duration": 1.835
        },
        {
            "text": "that we painted around the entire\nperimeter of the grocery store.",
            "start": 33.666,
            "duration": 3.237
        },
        {
            "text": "The challenge is over, and he walks\naway with his current winnings.",
            "start": 36.903,
            "duration": 2.469
        },
        {
            "text": "And to make sure\nhe stays inside.",
            "start": 39.372,
            "duration": 1.769
        },
        {
            "text": "It's worth noting here\nthat we have countless cameras",
            "start": 41.174,
            "duration": 2.603
        },
        {
            "text": "covering every square\ninch of the grocery store.",
            "start": 43.777,
            "duration": 2.235
        },
        {
            "text": "For my first meal on night one,\nI guess I'll cook this steak.",
            "start": 46.012,
            "duration": 2.736
        },
        {
            "text": "I think this is\njust going to be home base.",
            "start": 48.748,
            "duration": 1.669
        },
        {
            "text": "This little\ncorner of the grocery store.",
            "start": 50.417,
            "duration": 2.569
        },
        {
            "text": "If I have meals like this every night,\nI'll easily be here for years.",
            "start": 52.986,
            "duration": 3.203
        },
        {
            "text": "Day one, complete. See you in the morning.",
            "start": 56.222,
            "duration": 2.469
        },
        {
            "text": "It is officially been 24 hours,\nand I got the first 10 grand.",
            "start": 58.725,
            "duration": 2.869
        },
        {
            "text": "- Alex.\n- Hey.",
            "start": 61.594,
            "duration": 1.435
        },
        {
            "text": "Can you feel this and confirm it's $10,000?",
            "start": 63.096,
            "duration": 2.235
        },
        {
            "text": "It is.",
            "start": 67.7,
            "duration": 0.534
        },
        {
            "text": "I believe you.",
            "start": 68.234,
            "duration": 0.601
        },
        {
            "text": "Now, we introduced the twist\nof the challenge.",
            "start": 68.835,
            "duration": 2.336
        },
        {
            "text": "Basically,\nto receive the daily $10,000",
            "start": 71.171,
            "duration": 2.535
        },
        {
            "text": "you need to give me $10,000\nin product from the store.",
            "start": 73.773,
            "duration": 2.936
        },
        {
            "text": "And so you have to strategize\n what order to get rid of these items",
            "start": 76.709,
            "duration": 3.204
        },
        {
            "text": "to stay here as long as possible.",
            "start": 79.913,
            "duration": 1.868
        },
        {
            "text": "Okay.",
            "start": 82.916,
            "duration": 0.5
        },
        {
            "text": "Conveniently,\nthere's a lot of electronics over there",
            "start": 83.416,
            "duration": 2.002
        },
        {
            "text": "that are pretty\nexpensive for day one.",
            "start": 85.418,
            "duration": 1.201
        },
        {
            "text": "That's probably a good idea.",
            "start": 86.653,
            "duration": 1.168
        },
        {
            "text": "I can't really eat a TV,\nso it's no use to me.",
            "start": 87.821,
            "duration": 2.769
        },
        {
            "text": "You're $0.22 over.",
            "start": 91.524,
            "duration": 1.635
        },
        {
            "text": "All right, let me check out.",
            "start": 93.159,
            "duration": 1.568
        },
        {
            "text": "- Do you have an MVP card?\n- No.",
            "start": 94.727,
            "duration": 1.569
        },
        {
            "text": "- Would you like one?\n- No.",
            "start": 96.329,
            "duration": 0.968
        },
        {
            "text": "- Do you want to sign up for it?\n- No.",
            "start": 97.297,
            "duration": 1.535
        },
        {
            "text": "Here's your cash.",
            "start": 98.932,
            "duration": 0.8
        },
        {
            "text": "Kris, take it away.",
            "start": 99.766,
            "duration": 1.134
        },
        {
            "text": "I will see you tomorrow\nwith another $10,000 in cash.",
            "start": 102.602,
            "duration": 3.003
        },
        {
            "text": "You should start strategizing\nwhat you're going to sell me.",
            "start": 105.638,
            "duration": 1.769
        },
        {
            "text": "This changes everything.",
            "start": 107.407,
            "duration": 1.034
        },
        {
            "text": "I got to start strategizing for the future.",
            "start": 108.441,
            "duration": 1.969
        },
        {
            "text": "I have to figure out all of\nthe stuff that I need to get rid of.",
            "start": 110.443,
            "duration": 3.137
        },
        {
            "text": "Pet food, pet items.",
            "start": 113.58,
            "duration": 1.668
        },
        {
            "text": "Jimmy cannot pay me\nto eat this stuff, I swear.",
            "start": 115.248,
            "duration": 3.07
        },
        {
            "text": "I got $10,000\nworth of dog food right here.",
            "start": 118.351,
            "duration": 2.736
        },
        {
            "text": "I think I'm just going to get some rest,\nwake up early...",
            "start": 121.154,
            "duration": 2.002
        },
        {
            "text": "because I'm going to have to prep\nmore items tomorrow.",
            "start": 123.523,
            "duration": 2.002
        },
        {
            "text": "I got a lot of work ahead of me.",
            "start": 125.792,
            "duration": 1.501
        },
        {
            "text": "- Alex.\n- What's up Jimmy?",
            "start": 130.363,
            "duration": 2.903
        },
        {
            "text": "Is that what you're selling to me\ntoday?",
            "start": 133.399,
            "duration": 1.202
        },
        {
            "text": "Today it's dog food.",
            "start": 134.601,
            "duration": 1.768
        },
        {
            "text": "Oh, my gosh.\nIt's going to take us forever to move.",
            "start": 136.369,
            "duration": 2.269
        },
        {
            "text": "Wait, can we do like a...",
            "start": 138.638,
            "duration": 1.435
        },
        {
            "text": "I let him clap.\nTransition, go for it.",
            "start": 140.34,
            "duration": 1.968
        },
        {
            "text": "There we go.",
            "start": 144.344,
            "duration": 0.901
        },
        {
            "text": "It's all over here at the register.\nIsn't that a cool effect?",
            "start": 145.245,
            "duration": 2.702
        },
        {
            "text": "I love Beast magic.",
            "start": 147.981,
            "duration": 1.034
        },
        {
            "text": "We're at $9,991.80,",
            "start": 149.015,
            "duration": 2.669
        },
        {
            "text": "And for the final item,\nwe are now at $10,045.",
            "start": 151.684,
            "duration": 4.772
        },
        {
            "text": "And something you should know.",
            "start": 156.456,
            "duration": 1.134
        },
        {
            "text": "Every single item Alex sells to me,",
            "start": 157.59,
            "duration": 1.835
        },
        {
            "text": "we're literally going to donate\nto charity.",
            "start": 159.425,
            "duration": 1.502
        },
        {
            "text": "So don't worry, none of\nthis is going to go to waste.",
            "start": 160.927,
            "duration": 1.768
        },
        {
            "text": "The next few days\nwere kind of a breeze for Alex.",
            "start": 162.729,
            "duration": 2.135
        },
        {
            "text": "On day five,\nhe sold me $10,000 worth of produce.",
            "start": 164.898,
            "duration": 2.969
        },
        {
            "text": "All this produce here,\nthey're going to go bad very fast.",
            "start": 167.901,
            "duration": 2.936
        },
        {
            "text": "On day six, he sold me a bunch of diapers.",
            "start": 170.837,
            "duration": 2.002
        },
        {
            "text": "And on days seven, eight and nine,",
            "start": 172.972,
            "duration": 1.569
        },
        {
            "text": "he cleared out an additional\n$30,000 worth of products.",
            "start": 174.574,
            "duration": 3.07
        },
        {
            "text": "He even discovered\nthe backroom of the store,",
            "start": 177.677,
            "duration": 2.102
        },
        {
            "text": "and since he hasn't showered in 10 days,",
            "start": 179.812,
            "duration": 2.002
        },
        {
            "text": "he built his very own makeshift shower...",
            "start": 181.848,
            "duration": 2.002
        },
        {
            "text": "and laundry system.",
            "start": 184.817,
            "duration": 1.302
        },
        {
            "text": "- Hey, how's it going?\n- What's up, Jimmy?",
            "start": 187.32,
            "duration": 2.336
        },
        {
            "text": "All right,\nas of now, give me an honest answer.",
            "start": 189.656,
            "duration": 2.068
        },
        {
            "text": "How far do you think\nyou're going to go?",
            "start": 191.791,
            "duration": 1.468
        },
        {
            "text": "Oh, I mean,\nI feel like 100 days for sure.",
            "start": 193.259,
            "duration": 2.569
        },
        {
            "text": "Oh, boy.",
            "start": 195.862,
            "duration": 0.6
        },
        {
            "text": "Depending on how long Alex lasts,",
            "start": 196.462,
            "duration": 1.602
        },
        {
            "text": "this may just become\nmy most expensive video ever,",
            "start": 198.097,
            "duration": 2.87
        },
        {
            "text": "but I'm prepared for that.",
            "start": 201.0,
            "duration": 1.835
        },
        {
            "text": "Holy crap, dude.",
            "start": 204.771,
            "duration": 1.201
        },
        {
            "text": "I don't care if you go a year,\nI got the money.",
            "start": 206.005,
            "duration": 1.902
        },
        {
            "text": "Who put all this in here,\nis what I want to know?",
            "start": 207.941,
            "duration": 2.202
        },
        {
            "text": "The bank.",
            "start": 210.176,
            "duration": 0.701
        },
        {
            "text": "You will get this once\nI get my $10,000 in items.",
            "start": 210.91,
            "duration": 2.97
        },
        {
            "text": "All right,\ntoday I have more TVs.",
            "start": 214.047,
            "duration": 2.869
        },
        {
            "text": "Who goes to a grocery store\nto buy a TV?",
            "start": 216.916,
            "duration": 2.67
        },
        {
            "text": "Why are these here?",
            "start": 219.619,
            "duration": 1.068
        },
        {
            "text": "Now, Alex, be honest with me.",
            "start": 220.687,
            "duration": 1.301
        },
        {
            "text": "Did you empty out\nany of these TV boxes,",
            "start": 221.988,
            "duration": 1.735
        },
        {
            "text": "fill them with rocks and keep the TV?",
            "start": 223.723,
            "duration": 1.401
        },
        {
            "text": "Dogs.",
            "start": 227.56,
            "duration": 1.001
        },
        {
            "text": "All right. I trust him.",
            "start": 230.063,
            "duration": 0.8
        },
        {
            "text": "Even though\nthat was not what I was asking.",
            "start": 230.863,
            "duration": 1.802
        },
        {
            "text": "Approaching day 11,",
            "start": 236.669,
            "duration": 1.302
        },
        {
            "text": "Alex began to get pretty efficient\nat picking which items to sell.",
            "start": 237.971,
            "duration": 2.936
        },
        {
            "text": "$10,001.89.",
            "start": 241.741,
            "duration": 1.935
        },
        {
            "text": "And since I had to leave to go film a video\nwhere I stranded myself on an island...",
            "start": 243.876,
            "duration": 3.738
        },
        {
            "text": "This is not comfortable.",
            "start": 247.68,
            "duration": 1.235
        },
        {
            "text": "But let's pray we get like\n30 minutes of sleep tonight.",
            "start": 248.948,
            "duration": 2.803
        },
        {
            "text": "We had someone else\ndrop off the money for Alex.",
            "start": 251.751,
            "duration": 2.336
        },
        {
            "text": "We call him \"The Money Man\".",
            "start": 254.22,
            "duration": 1.301
        },
        {
            "text": "It's \"The Money Man\".",
            "start": 255.521,
            "duration": 2.269
        },
        {
            "text": "Thank you, sir.",
            "start": 259.092,
            "duration": 0.667
        },
        {
            "text": "$100,000.",
            "start": 259.792,
            "duration": 1.502
        },
        {
            "text": "I can definitely reach a million.",
            "start": 261.327,
            "duration": 1.835
        },
        {
            "text": "And what he did\nwith the rest of his time",
            "start": 263.196,
            "duration": 1.668
        },
        {
            "text": "to keep himself\nentertained was interesting.",
            "start": 264.864,
            "duration": 2.669
        },
        {
            "text": "I am building a cheeseball wall.",
            "start": 267.533,
            "duration": 2.236
        },
        {
            "text": "It's done.",
            "start": 270.937,
            "duration": 0.867
        },
        {
            "text": "The great wall of cheese balls.",
            "start": 271.838,
            "duration": 2.269
        },
        {
            "text": "Oh, yeah baby.\nHere we go.",
            "start": 275.908,
            "duration": 1.902
        },
        {
            "text": "Three, two, one...",
            "start": 277.944,
            "duration": 1.535
        },
        {
            "text": "It was worth it.",
            "start": 283.416,
            "duration": 1.668
        },
        {
            "text": "It was so worth it.",
            "start": 285.118,
            "duration": 1.568
        },
        {
            "text": "On day 13,",
            "start": 288.121,
            "duration": 0.967
        },
        {
            "text": "Alex decided to upgrade\nhis shower because...",
            "start": 289.088,
            "duration": 2.57
        },
        {
            "text": "It's a piece of crap.",
            "start": 291.658,
            "duration": 1.568
        },
        {
            "text": "What I'm going to do,",
            "start": 294.227,
            "duration": 0.934
        },
        {
            "text": "is use four of these shelves\nto reinforce the shower.",
            "start": 295.194,
            "duration": 3.971
        },
        {
            "text": "Okay, here we go.",
            "start": 299.365,
            "duration": 1.001
        },
        {
            "text": "I am going to use plastic liner,\ndrape it across here.",
            "start": 309.475,
            "duration": 3.27
        },
        {
            "text": "The walls are waterproof now.",
            "start": 312.812,
            "duration": 2.336
        },
        {
            "text": "All right,\nYou got to give it to him.",
            "start": 315.148,
            "duration": 1.368
        },
        {
            "text": "This man is literally constructing\na functioning shower",
            "start": 316.516,
            "duration": 3.203
        },
        {
            "text": "out of just raw store parts.",
            "start": 319.919,
            "duration": 1.902
        },
        {
            "text": "And there it is.\nShower's done.",
            "start": 321.821,
            "duration": 1.869
        },
        {
            "text": "Time to test it.",
            "start": 323.69,
            "duration": 1.334
        },
        {
            "text": "Okay.",
            "start": 331.064,
            "duration": 0.6
        },
        {
            "text": "It's been a few days in here.",
            "start": 331.664,
            "duration": 1.468
        },
        {
            "text": "I'm going to build a wall.",
            "start": 333.132,
            "duration": 1.035
        },
        {
            "text": "Now, I never thought I'd see this,",
            "start": 334.2,
            "duration": 1.235
        },
        {
            "text": "but Alex literally used\nall the water bottles",
            "start": 335.468,
            "duration": 2.502
        },
        {
            "text": "in the entire store to build walls",
            "start": 338.004,
            "duration": 1.668
        },
        {
            "text": "for his makeshift shelter.",
            "start": 339.706,
            "duration": 1.468
        },
        {
            "text": "He even created a bed\nusing all of the toilet paper",
            "start": 341.274,
            "duration": 2.469
        },
        {
            "text": "and it looked kind of comfortable.",
            "start": 343.976,
            "duration": 1.535
        },
        {
            "text": "This is pretty cozy.",
            "start": 345.978,
            "duration": 1.502
        },
        {
            "text": "I could fall asleep right here.",
            "start": 347.48,
            "duration": 1.668
        },
        {
            "text": "I got to get to scan in,",
            "start": 355.788,
            "duration": 0.868
        },
        {
            "text": "kind of had my eyes\non these bad boys for a while.",
            "start": 356.689,
            "duration": 2.936
        },
        {
            "text": "Gift cards.\nThese things are freaking expensive.",
            "start": 359.692,
            "duration": 2.569
        },
        {
            "text": "It is actually surprising\nhow expensive birthday cards are.",
            "start": 362.328,
            "duration": 3.07
        },
        {
            "text": "Because Alex was able to hit his\n$10,000 mark only using the cards.",
            "start": 365.431,
            "duration": 4.371
        },
        {
            "text": "And after I got back\nfrom filming at the island...",
            "start": 369.802,
            "duration": 2.002
        },
        {
            "text": "- Hey, Jimmy.\n- Hey, it's been a while.",
            "start": 371.838,
            "duration": 1.668
        },
        {
            "text": "Alex wanted to see if we could help him\nuse the forklift in the back of the store.",
            "start": 373.539,
            "duration": 3.37
        },
        {
            "text": "You know, if you could get it in\nthe store, that'd be super helpful.",
            "start": 376.943,
            "duration": 2.536
        },
        {
            "text": "You're sure you're going\nto let Kris drive this?",
            "start": 379.512,
            "duration": 1.935
        },
        {
            "text": "Yeah.",
            "start": 381.447,
            "duration": 0.401
        },
        {
            "text": "Three, two...",
            "start": 381.914,
            "duration": 1.435
        },
        {
            "text": "Alright.",
            "start": 386.052,
            "duration": 0.6
        },
        {
            "text": "Not the bakery.",
            "start": 386.652,
            "duration": 1.268
        },
        {
            "text": "I think maybe one more.",
            "start": 387.954,
            "duration": 1.835
        },
        {
            "text": "Yeah.",
            "start": 392.225,
            "duration": 1.568
        },
        {
            "text": "Hey, it's in.",
            "start": 395.661,
            "duration": 1.202
        },
        {
            "text": "Yes!",
            "start": 396.896,
            "duration": 1.335
        },
        {
            "text": "Yeah, yeah, yeah.",
            "start": 398.297,
            "duration": 1.836
        },
        {
            "text": "Enjoy your forklift.",
            "start": 400.133,
            "duration": 0.934
        },
        {
            "text": "We'll see you tomorrow.",
            "start": 401.1,
            "duration": 1.168
        },
        {
            "text": "Even though it's only been a day\nsince he last saw me,",
            "start": 402.668,
            "duration": 2.203
        },
        {
            "text": "it seemed like Alex\nreally started to miss me.",
            "start": 405.004,
            "duration": 2.436
        },
        {
            "text": "At least that's the only explanation\nI have for what he's about to do.",
            "start": 407.507,
            "duration": 2.936
        },
        {
            "text": "I saw this\ncut out of Jimmy over here.",
            "start": 410.476,
            "duration": 2.036
        },
        {
            "text": "We're going to be hanging out a lot,\nyou and I.",
            "start": 412.812,
            "duration": 1.768
        },
        {
            "text": "He's just going to watch,\nmake sure I don't lose count.",
            "start": 414.58,
            "duration": 2.503
        },
        {
            "text": "Just scanning away for another 10k.",
            "start": 417.15,
            "duration": 3.37
        },
        {
            "text": "$10,000.33",
            "start": 420.553,
            "duration": 2.87
        },
        {
            "text": "Over the next few days,",
            "start": 423.456,
            "duration": 1.068
        },
        {
            "text": "Alex's efficiency was through\nthe roof,",
            "start": 424.557,
            "duration": 2.035
        },
        {
            "text": "thanks to his new forklift.",
            "start": 426.592,
            "duration": 1.168
        },
        {
            "text": "So he even had enough time\nto upgrade his bed.",
            "start": 427.76,
            "duration": 2.169
        },
        {
            "text": "and it was quite the improvement.",
            "start": 429.996,
            "duration": 1.535
        },
        {
            "text": "It's is so much better.",
            "start": 432.098,
            "duration": 1.601
        },
        {
            "text": "And even though Alex's original goal\nwas to get a million dollars...",
            "start": 433.699,
            "duration": 3.37
        },
        {
            "text": "I think we're going\nfor a mil on this one.",
            "start": 437.069,
            "duration": 1.802
        },
        {
            "text": "I hope not. He started documenting\nwhat he'd spend the money on",
            "start": 438.905,
            "duration": 2.736
        },
        {
            "text": "and came to realize maybe he didn't\nneed to stay as long as he thought.",
            "start": 441.641,
            "duration": 3.503
        },
        {
            "text": "A million dollars is nice in theory.",
            "start": 445.378,
            "duration": 2.702
        },
        {
            "text": "I'm still missing out\ntime with my boys.",
            "start": 448.08,
            "duration": 2.203
        },
        {
            "text": "Both their birthdays are coming up\nin the next two months.",
            "start": 450.316,
            "duration": 2.87
        },
        {
            "text": "I've never missed a birthday yet.",
            "start": 453.186,
            "duration": 1.268
        },
        {
            "text": "So after thinking about\nwhat I want to put the money toward,",
            "start": 454.52,
            "duration": 2.569
        },
        {
            "text": "I realized that I need to\nat least make $500,000.",
            "start": 457.156,
            "duration": 3.737
        },
        {
            "text": "But right now, I only have $200,000.",
            "start": 460.927,
            "duration": 2.435
        },
        {
            "text": "So in total, I got 50 days,",
            "start": 463.529,
            "duration": 1.602
        },
        {
            "text": "I got to be in here\nalmost halfway there.",
            "start": 465.131,
            "duration": 2.035
        },
        {
            "text": "On day 22,\nAlex decided to absolutely decimate",
            "start": 467.834,
            "duration": 3.47
        },
        {
            "text": "all the goldfish in the grocery\nstore.",
            "start": 471.304,
            "duration": 1.434
        },
        {
            "text": "Oh, my God.",
            "start": 472.772,
            "duration": 1.101
        },
        {
            "text": "Okay, so this is $10,000\nworth of goldfish.",
            "start": 474.006,
            "duration": 4.371
        },
        {
            "text": "I could feed an army of toddlers.",
            "start": 478.377,
            "duration": 2.536
        },
        {
            "text": "All right.",
            "start": 481.414,
            "duration": 0.634
        },
        {
            "text": "Thank you, sir.",
            "start": 482.048,
            "duration": 0.867
        },
        {
            "text": "You're living a regular life\nnow. Almost.",
            "start": 482.915,
            "duration": 2.469
        },
        {
            "text": "You're getting paid\nten grand a day to miss your family.",
            "start": 485.551,
            "duration": 2.403
        },
        {
            "text": "Yeah.",
            "start": 488.221,
            "duration": 0.9
        },
        {
            "text": "And you can just do this\nhowever long you want.",
            "start": 489.155,
            "duration": 1.835
        },
        {
            "text": "Yeah.",
            "start": 491.057,
            "duration": 0.801
        },
        {
            "text": "And you can just do this\nhowever long you want.",
            "start": 491.891,
            "duration": 1.902
        },
        {
            "text": "However long you want.",
            "start": 494.16,
            "duration": 1.101
        },
        {
            "text": "However long you want.",
            "start": 495.962,
            "duration": 1.101
        },
        {
            "text": "As you can see, the days\nstarted blending together for Alex.",
            "start": 499.532,
            "duration": 3.37
        },
        {
            "text": "But eventually, the day came\nwhere he decided to sell the water",
            "start": 503.603,
            "duration": 2.769
        },
        {
            "text": "that he originally used for his shelter.",
            "start": 506.405,
            "duration": 2.002
        },
        {
            "text": "But since he couldn't\nsell the empty shelves in the store,",
            "start": 508.941,
            "duration": 2.57
        },
        {
            "text": "he realized\nthey make pretty good walls.",
            "start": 511.644,
            "duration": 2.236
        },
        {
            "text": "I'm going to reinforce\nthe house with metal shelves.",
            "start": 513.913,
            "duration": 3.57
        },
        {
            "text": "This is the way.",
            "start": 521.888,
            "duration": 2.002
        },
        {
            "text": "As you can see, Alex is feeling\npretty at home now.",
            "start": 529.862,
            "duration": 2.569
        },
        {
            "text": "But what he doesn't know is\nwhen I bought this grocery store,",
            "start": 532.565,
            "duration": 2.869
        },
        {
            "text": "I stopped\npaying the electricity bill.",
            "start": 535.434,
            "duration": 1.869
        },
        {
            "text": "So at any point now,\nall the power's going to cut off",
            "start": 537.303,
            "duration": 2.336
        },
        {
            "text": "and his freezers won't work,\nthe lights won't work, and so much more.",
            "start": 539.639,
            "duration": 2.702
        },
        {
            "text": "The challenge is going to get way harder.",
            "start": 542.975,
            "duration": 1.402
        },
        {
            "text": "But to give them some motivation\nbefore things get pretty crazy.",
            "start": 544.377,
            "duration": 2.802
        },
        {
            "text": "We thought Alex deserved a reward.",
            "start": 547.213,
            "duration": 1.735
        },
        {
            "text": "- Are you excited to see your dad?\n- Yes.",
            "start": 548.948,
            "duration": 1.835
        },
        {
            "text": "- You ready to do this?\n- Yeah.",
            "start": 550.783,
            "duration": 1.502
        },
        {
            "text": "I think he might literally cry.\nThis is gonna be crazy.",
            "start": 552.285,
            "duration": 2.102
        },
        {
            "text": "Alex, we have a surprise for you.",
            "start": 555.521,
            "duration": 2.202
        },
        {
            "text": "Hello.",
            "start": 557.79,
            "duration": 1.101
        },
        {
            "text": "- Oh, my babies!\n- We brought some special guests",
            "start": 559.258,
            "duration": 1.935
        },
        {
            "text": "Hi buddy!",
            "start": 561.26,
            "duration": 1.168
        },
        {
            "text": "Yesterday, you were telling me about\nhow much you miss your family.",
            "start": 562.428,
            "duration": 2.769
        },
        {
            "text": "I felt kind of bad.",
            "start": 565.197,
            "duration": 0.868
        },
        {
            "text": "So to celebrate 30 days,",
            "start": 566.065,
            "duration": 1.368
        },
        {
            "text": "we're gonna\nto let you spend the day with them.",
            "start": 567.433,
            "duration": 1.268
        },
        {
            "text": "What are you doing? You crazy boy.",
            "start": 570.169,
            "duration": 1.935
        },
        {
            "text": "Daddy, I need to go pee.",
            "start": 572.104,
            "duration": 2.169
        },
        {
            "text": "What's happening\nwith all the boxes on the floor?",
            "start": 575.541,
            "duration": 2.169
        },
        {
            "text": "I made a race car track.",
            "start": 577.944,
            "duration": 1.134
        },
        {
            "text": "- Is that the car?\n- Yeah",
            "start": 579.111,
            "duration": 1.635
        },
        {
            "text": "Wait, can he ride that?",
            "start": 580.78,
            "duration": 1.368
        },
        {
            "text": "What do you think, dude?",
            "start": 583.749,
            "duration": 1.368
        },
        {
            "text": "There they are.",
            "start": 586.786,
            "duration": 1.234
        },
        {
            "text": "I can't believe that you guys are here.",
            "start": 589.188,
            "duration": 1.568
        },
        {
            "text": "I know.",
            "start": 590.756,
            "duration": 1.101
        },
        {
            "text": "- Dada.\n- Come here.",
            "start": 592.224,
            "duration": 1.936
        },
        {
            "text": "Today, I got to see Sarah and the boys.",
            "start": 594.36,
            "duration": 1.501
        },
        {
            "text": "It was freaking amazing.",
            "start": 595.861,
            "duration": 1.302
        },
        {
            "text": "And Sarah was as beautiful as ever.",
            "start": 597.163,
            "duration": 1.935
        },
        {
            "text": "- I love you.\n- I love you.",
            "start": 599.098,
            "duration": 2.202
        },
        {
            "text": "- Bye.\n- Bye buddy, I love you.",
            "start": 602.001,
            "duration": 1.301
        },
        {
            "text": "Heart break.",
            "start": 606.072,
            "duration": 1.601
        },
        {
            "text": "When I saw my kids,\nI mean, they looked different to me,",
            "start": 607.707,
            "duration": 3.27
        },
        {
            "text": "you know at that age,",
            "start": 611.01,
            "duration": 1.001
        },
        {
            "text": "they grow weekly.",
            "start": 612.011,
            "duration": 2.069
        },
        {
            "text": "I just look forward to going back\nhome, spending time with my family.",
            "start": 614.08,
            "duration": 3.436
        },
        {
            "text": "What's up? I better get up\nand start scanning stuff now.",
            "start": 619.285,
            "duration": 3.136
        },
        {
            "text": "We're gonna...",
            "start": 622.722,
            "duration": 1.301
        },
        {
            "text": "What the heck? Why are the lights off?",
            "start": 624.023,
            "duration": 2.436
        },
        {
            "text": "What are these shenanigans?",
            "start": 626.592,
            "duration": 1.869
        },
        {
            "text": "There's a flashlight.",
            "start": 628.461,
            "duration": 1.168
        },
        {
            "text": "It's just some kind of joke?",
            "start": 629.629,
            "duration": 1.868
        },
        {
            "text": "Houston, we have a problem.",
            "start": 631.497,
            "duration": 2.035
        },
        {
            "text": "Did you do this, sir?",
            "start": 633.532,
            "duration": 2.736
        },
        {
            "text": "Knock, knock.",
            "start": 637.937,
            "duration": 0.934
        },
        {
            "text": "This is so much creepier.",
            "start": 639.805,
            "duration": 1.402
        },
        {
            "text": "My power's out, Jimmy.",
            "start": 641.24,
            "duration": 1.301
        },
        {
            "text": "Yes, so when I bought this grocery store,\nthey gave me a form to put,",
            "start": 642.575,
            "duration": 3.537
        },
        {
            "text": "like, the utilities in my name,\nand I just never filled it out.",
            "start": 646.112,
            "duration": 2.502
        },
        {
            "text": "The cameras and cash registers\nare hooked up to a generator",
            "start": 649.849,
            "duration": 2.602
        },
        {
            "text": "because we need those.\nSo what am I looking at over here?",
            "start": 652.685,
            "duration": 2.402
        },
        {
            "text": "Okay, so I had originally $60,000\nready to go.",
            "start": 655.121,
            "duration": 3.77
        },
        {
            "text": "Oh, my gosh.",
            "start": 658.891,
            "duration": 0.768
        },
        {
            "text": "But I assumed\nnow that the power went out,",
            "start": 659.659,
            "duration": 1.601
        },
        {
            "text": "You're going to sell the frozen\nstuff...",
            "start": 661.26,
            "duration": 1.702
        },
        {
            "text": "Yeah. Things have changed.",
            "start": 662.962,
            "duration": 1.301
        },
        {
            "text": "We need to get to scan it.",
            "start": 664.296,
            "duration": 1.168
        },
        {
            "text": "Let's get rid\nof these hot meats.",
            "start": 665.464,
            "duration": 1.035
        },
        {
            "text": "Assembly line.",
            "start": 666.532,
            "duration": 0.767
        },
        {
            "text": "All right, I'll hold the cart.",
            "start": 667.299,
            "duration": 1.535
        },
        {
            "text": "Assembly line.",
            "start": 668.868,
            "duration": 0.734
        },
        {
            "text": "I'm the door holder.",
            "start": 669.602,
            "duration": 0.967
        },
        {
            "text": "And while they're clearing out\nthe freezers,",
            "start": 670.569,
            "duration": 1.702
        },
        {
            "text": "I want to tell you guys\nabout Shopify.",
            "start": 672.271,
            "duration": 1.702
        },
        {
            "text": "Shopify\nhelp pay for this grocery store.",
            "start": 673.973,
            "duration": 1.868
        },
        {
            "text": "And in exchange,\nwanted me to promote",
            "start": 675.841,
            "duration": 1.502
        },
        {
            "text": "one of the millions of businesses\nthey support in power.",
            "start": 677.343,
            "duration": 2.269
        },
        {
            "text": "If only we had a bag that we could\nput these things in to keep it cold.",
            "start": 679.612,
            "duration": 2.936
        },
        {
            "text": "And together we picked Kanga Coolers.",
            "start": 682.581,
            "duration": 1.869
        },
        {
            "text": "Chandler, what if I told you,\nthere's a 12 pack of soda inside of it?",
            "start": 684.483,
            "duration": 2.97
        },
        {
            "text": "And it can keep what's inside cold\nfor up to seven hours.",
            "start": 688.02,
            "duration": 2.903
        },
        {
            "text": "That's a long time.",
            "start": 692.692,
            "duration": 0.867
        },
        {
            "text": "You got multi wieners.\nYou got single wieners.",
            "start": 693.559,
            "duration": 2.402
        },
        {
            "text": "- Cheesy.\n- Cheesy wieners.",
            "start": 695.961,
            "duration": 1.268
        },
        {
            "text": "Kanga Coolers are\nlightweight and insulated,",
            "start": 697.229,
            "duration": 2.203
        },
        {
            "text": "so you can take them wherever.",
            "start": 699.465,
            "duration": 1.435
        },
        {
            "text": "Hey, meet us at the front.",
            "start": 700.933,
            "duration": 1.568
        },
        {
            "text": "Chandler, have you ever been\na cashier before?",
            "start": 702.535,
            "duration": 1.334
        },
        {
            "text": "- Yeah.\n- Wait, did you double scan that? Hold up.",
            "start": 703.869,
            "duration": 2.203
        },
        {
            "text": "You can have the Kanga Cooler.",
            "start": 706.072,
            "duration": 1.034
        },
        {
            "text": "You can fit a\nhuman head in here.",
            "start": 707.106,
            "duration": 1.368
        },
        {
            "text": "Anyways, click the link in the description,\ndownload the shop app right now.",
            "start": 708.507,
            "duration": 2.136
        },
        {
            "text": "You can buy a Kanga Cooler.",
            "start": 710.676,
            "duration": 1.168
        },
        {
            "text": "I'm going to go help them\nscan some meat.",
            "start": 711.877,
            "duration": 1.635
        },
        {
            "text": "All right, here's our meat receipt.",
            "start": 713.512,
            "duration": 1.902
        },
        {
            "text": "Here's your 10 grand.",
            "start": 716.849,
            "duration": 1.101
        },
        {
            "text": "Also, here's a Kanga Cooler.",
            "start": 717.95,
            "duration": 1.668
        },
        {
            "text": "Oh, nice.",
            "start": 719.618,
            "duration": 0.701
        },
        {
            "text": "Oh by the way Alex,\nI\u2019m going to Africa for a week",
            "start": 720.319,
            "duration": 2.236
        },
        {
            "text": "At this point, I once again had to\nleave to go film a video in Africa",
            "start": 722.555,
            "duration": 3.47
        },
        {
            "text": "where I built a hundred wells.",
            "start": 726.058,
            "duration": 1.435
        },
        {
            "text": "Well number one is a success.",
            "start": 727.56,
            "duration": 2.002
        },
        {
            "text": "Alex spend the rest of his day",
            "start": 729.562,
            "duration": 1.535
        },
        {
            "text": "rushing to get all the frozen\nfood sold so it can be donated.",
            "start": 731.097,
            "duration": 2.836
        },
        {
            "text": "Guess I'll just be scanning stuff\nin the dark from now on.",
            "start": 733.933,
            "duration": 2.969
        },
        {
            "text": "I really hope Jimmy turns the power on.",
            "start": 737.103,
            "duration": 2.335
        },
        {
            "text": "It's going to suck.",
            "start": 739.438,
            "duration": 1.035
        },
        {
            "text": "I'm not going to lie.",
            "start": 740.473,
            "duration": 0.9
        },
        {
            "text": "Being left without power affected\nAlex way more than I thought it would.",
            "start": 741.373,
            "duration": 3.704
        },
        {
            "text": "I guess the food wasn't\nthe only thing getting checked out.",
            "start": 745.077,
            "duration": 3.003
        },
        {
            "text": "I wonder if you can tip over a forklift?",
            "start": 752.752,
            "duration": 2.569
        },
        {
            "text": "Careful on aisle seven.",
            "start": 758.257,
            "duration": 2.102
        },
        {
            "text": "This store is turning into a wasteland.",
            "start": 769.735,
            "duration": 2.536
        },
        {
            "text": "So I'm going to the back.",
            "start": 772.671,
            "duration": 1.435
        },
        {
            "text": " I'm going to open up this dock door\nand let some daylight hit my face,",
            "start": 774.106,
            "duration": 4.605
        },
        {
            "text": "breathe in some fresh air\nbecause this is not going to do it.",
            "start": 778.778,
            "duration": 3.837
        },
        {
            "text": "It's so nice.",
            "start": 785.451,
            "duration": 1.168
        },
        {
            "text": "This right here\nwill give me through the dark days.",
            "start": 786.919,
            "duration": 3.604
        },
        {
            "text": "It is day 36.",
            "start": 792.291,
            "duration": 1.535
        },
        {
            "text": "I got $360,000.",
            "start": 793.859,
            "duration": 3.938
        },
        {
            "text": "Why stop now?",
            "start": 797.83,
            "duration": 1.268
        },
        {
            "text": "Got to keep loading these carts up.\nGot a lot of food to get through.",
            "start": 799.131,
            "duration": 3.37
        },
        {
            "text": "Just carts and pools of money.",
            "start": 802.535,
            "duration": 2.869
        },
        {
            "text": "And waiting,",
            "start": 805.437,
            "duration": 1.102
        },
        {
            "text": "waiting for the days to go by.",
            "start": 806.572,
            "duration": 1.702
        },
        {
            "text": "The most exciting part of my day\nis being this close to the red line.",
            "start": 809.475,
            "duration": 3.87
        },
        {
            "text": "I'm just a sad,\nold miserable boy back here.",
            "start": 813.379,
            "duration": 5.772
        },
        {
            "text": "Nothing's ever been sadder in my life,",
            "start": 819.485,
            "duration": 4.471
        },
        {
            "text": "except living in a grocery store.",
            "start": 824.023,
            "duration": 3.37
        },
        {
            "text": "Coffee, food, and a lot of money.",
            "start": 827.827,
            "duration": 2.702
        },
        {
            "text": "I'm like way ahead on checkouts still.",
            "start": 830.563,
            "duration": 1.901
        },
        {
            "text": "I don't want to do anything,\nthere's nothing to do.",
            "start": 832.498,
            "duration": 2.869
        },
        {
            "text": "All that stands between me,\nmy wife, my kids,",
            "start": 835.935,
            "duration": 3.236
        },
        {
            "text": "is this line right here.",
            "start": 839.338,
            "duration": 1.268
        },
        {
            "text": "The lights being off,",
            "start": 840.606,
            "duration": 1.068
        },
        {
            "text": "being this close to the red line,\nrealizing I can go see my family.",
            "start": 841.674,
            "duration": 3.937
        },
        {
            "text": "It's super tempting every day now",
            "start": 845.744,
            "duration": 2.036
        },
        {
            "text": "I know there's\na bunch of pallets back there still",
            "start": 849.982,
            "duration": 2.269
        },
        {
            "text": "that I haven't even dug into.",
            "start": 852.284,
            "duration": 1.502
        },
        {
            "text": "Some glasses.",
            "start": 853.786,
            "duration": 1.268
        },
        {
            "text": "Ice packs.",
            "start": 855.154,
            "duration": 1.468
        },
        {
            "text": "What the...",
            "start": 857.022,
            "duration": 0.935
        },
        {
            "text": "Look what I just found.",
            "start": 858.424,
            "duration": 0.867
        },
        {
            "text": "InstaStart QuickPack lantern.",
            "start": 859.291,
            "duration": 2.803
        },
        {
            "text": "Nice.",
            "start": 862.261,
            "duration": 0.801
        },
        {
            "text": "I got five of them.",
            "start": 863.062,
            "duration": 1.234
        },
        {
            "text": "I just lit them all up.",
            "start": 864.396,
            "duration": 1.402
        },
        {
            "text": "They're on full blast right now.",
            "start": 865.798,
            "duration": 1.768
        },
        {
            "text": "It definitely lights up\nthe entire space really well.",
            "start": 867.566,
            "duration": 3.17
        },
        {
            "text": "I feel like I can actually\nhang out in here again.",
            "start": 870.736,
            "duration": 2.035
        },
        {
            "text": "Alex, are you here?",
            "start": 875.341,
            "duration": 1.301
        },
        {
            "text": "- Another 10k?\n- Yeah",
            "start": 877.443,
            "duration": 1.201
        },
        {
            "text": "Let's go, dude.",
            "start": 878.677,
            "duration": 0.901
        },
        {
            "text": "It's crazy I have all this money.",
            "start": 879.612,
            "duration": 1.668
        },
        {
            "text": "But there's nothing I can do\nwith this money while I'm in here.",
            "start": 881.38,
            "duration": 2.936
        },
        {
            "text": "Except just look at it.",
            "start": 884.35,
            "duration": 1.134
        },
        {
            "text": "Well, you can't look at it.\nIt's so dark in here.",
            "start": 885.517,
            "duration": 2.269
        },
        {
            "text": "- So I'm going to bring some lights in.\n- Are you serious?",
            "start": 887.887,
            "duration": 2.435
        },
        {
            "text": "For filming purposes.",
            "start": 890.356,
            "duration": 1.034
        },
        {
            "text": "Alright.",
            "start": 891.39,
            "duration": 0.834
        },
        {
            "text": "What are you going to do for\nthe rest of the time you're in here?",
            "start": 892.258,
            "duration": 1.601
        },
        {
            "text": "Something I definitely want to do\nis go ahead and just run",
            "start": 893.859,
            "duration": 2.169
        },
        {
            "text": "through all these shells\nwith the forklift.",
            "start": 896.028,
            "duration": 2.135
        },
        {
            "text": "You ask for this!",
            "start": 904.203,
            "duration": 1.301
        },
        {
            "text": "What is going on?",
            "start": 907.172,
            "duration": 1.502
        },
        {
            "text": "All right.",
            "start": 908.674,
            "duration": 0.867
        },
        {
            "text": "Time for me to not be here anymore.\nWe'll see you tomorrow.",
            "start": 909.541,
            "duration": 3.27
        },
        {
            "text": "Here's your broom.",
            "start": 913.145,
            "duration": 1.335
        },
        {
            "text": "Thanks, guys.",
            "start": 914.48,
            "duration": 0.734
        },
        {
            "text": "Enjoy cleaning.",
            "start": 915.214,
            "duration": 1.168
        },
        {
            "text": "After spending an entire day\ncleaning up Kris's mess,",
            "start": 916.382,
            "duration": 3.036
        },
        {
            "text": "Alex took advantage of the newly\nopened space to set up a pool",
            "start": 919.418,
            "duration": 3.003
        },
        {
            "text": "he found in the back.",
            "start": 922.421,
            "duration": 0.834
        },
        {
            "text": "Off we go.",
            "start": 923.289,
            "duration": 1.001
        },
        {
            "text": "I'm going to drag the hose out here,\nstick it in this pool,",
            "start": 926.725,
            "duration": 3.037
        },
        {
            "text": "and sometime tomorrow\nwe'll have a grocery swimming pool.",
            "start": 929.762,
            "duration": 4.037
        },
        {
            "text": "It's been over a week, and Chandler",
            "start": 934.333,
            "duration": 1.301
        },
        {
            "text": "won't tell me what happened\nwhile I was gone.",
            "start": 935.634,
            "duration": 1.802
        },
        {
            "text": "This place looks\ncompletely different.",
            "start": 937.436,
            "duration": 1.568
        },
        {
            "text": "Oh God, open the doors.\nI got to see this.",
            "start": 939.004,
            "duration": 1.969
        },
        {
            "text": "Where did everything go?",
            "start": 941.974,
            "duration": 1.268
        },
        {
            "text": "We did a little remodeling\nwhile you were gone.",
            "start": 943.242,
            "duration": 2.402
        },
        {
            "text": "This looks like someone gave Kris\na forklift. Everything makes sense now.",
            "start": 945.644,
            "duration": 2.936
        },
        {
            "text": "- Can you show me the pool?\n- Yeah, you want to get in?",
            "start": 948.881,
            "duration": 1.968
        },
        {
            "text": "Flip.",
            "start": 950.849,
            "duration": 1.702
        },
        {
            "text": "Do you wear socks?",
            "start": 952.551,
            "duration": 1.068
        },
        {
            "text": "Yeah.",
            "start": 953.619,
            "duration": 0.567
        },
        {
            "text": "That's crazy.",
            "start": 954.186,
            "duration": 1.301
        },
        {
            "text": "It's freezing.",
            "start": 958.157,
            "duration": 0.967
        },
        {
            "text": "Cannonball.",
            "start": 959.158,
            "duration": 1.001
        },
        {
            "text": "What you typically do\nin the pool?",
            "start": 961.226,
            "duration": 1.702
        },
        {
            "text": "I just kind of float around.",
            "start": 964.363,
            "duration": 1.735
        },
        {
            "text": "This was fun and all,\nbut I think we should check out.",
            "start": 966.665,
            "duration": 2.169
        },
        {
            "text": "Thanks for the groceries.\nEnjoy your pool.",
            "start": 968.834,
            "duration": 2.202
        },
        {
            "text": "All right, I'm just going\nto grab everything from the back",
            "start": 971.103,
            "duration": 2.87
        },
        {
            "text": "and just put it up\nhere, organize it.",
            "start": 974.006,
            "duration": 2.135
        },
        {
            "text": "And who knows?\nMaybe there's some fun in there.",
            "start": 976.175,
            "duration": 1.568
        },
        {
            "text": "It's no secret at this point,\nAlex was pretty tired,",
            "start": 977.743,
            "duration": 2.569
        },
        {
            "text": "and while he was making\nhis rounds in the forklift,",
            "start": 980.546,
            "duration": 2.436
        },
        {
            "text": "something unexpected happened.",
            "start": 983.048,
            "duration": 1.835
        },
        {
            "text": "Oh, crap.",
            "start": 985.05,
            "duration": 1.268
        },
        {
            "text": "No!",
            "start": 986.685,
            "duration": 1.935
        },
        {
            "text": "No!",
            "start": 989.521,
            "duration": 1.001
        },
        {
            "text": "Oh God!",
            "start": 990.589,
            "duration": 2.002
        },
        {
            "text": "Dude!",
            "start": 996.228,
            "duration": 1.301
        },
        {
            "text": "No!",
            "start": 998.797,
            "duration": 1.502
        },
        {
            "text": "Oh my God.",
            "start": 1001.633,
            "duration": 1.769
        },
        {
            "text": "I was trying to turn one way, and\nit just went the opposite direction.",
            "start": 1003.402,
            "duration": 3.003
        },
        {
            "text": "Oh, my God.",
            "start": 1006.805,
            "duration": 1.902
        },
        {
            "text": "My freaking money is soaked.",
            "start": 1008.707,
            "duration": 2.002
        },
        {
            "text": "There's a bunch of products ruined.",
            "start": 1010.709,
            "duration": 1.735
        },
        {
            "text": "It's, like, so deep right here.",
            "start": 1012.444,
            "duration": 2.436
        },
        {
            "text": "It's in my space.",
            "start": 1014.88,
            "duration": 1.435
        },
        {
            "text": "It's all over the grocery store.",
            "start": 1016.315,
            "duration": 1.735
        },
        {
            "text": "Dude, I'm done, man.",
            "start": 1018.05,
            "duration": 2.035
        },
        {
            "text": "I just want to leave.",
            "start": 1020.085,
            "duration": 1.402
        },
        {
            "text": "We're going in.",
            "start": 1022.955,
            "duration": 1.001
        },
        {
            "text": "- Alex!\n- Buddy.",
            "start": 1024.189,
            "duration": 1.569
        },
        {
            "text": "Why is it so wet in here?",
            "start": 1025.791,
            "duration": 1.068
        },
        {
            "text": "Yeah.",
            "start": 1026.859,
            "duration": 1.001
        },
        {
            "text": "Oh, Alex.",
            "start": 1028.794,
            "duration": 1.068
        },
        {
            "text": "Your golden chariot awaits you.",
            "start": 1029.862,
            "duration": 1.935
        },
        {
            "text": "Look at you in bed.",
            "start": 1032.364,
            "duration": 1.135
        },
        {
            "text": "- You good dog?\n- I'm all right, man.",
            "start": 1033.532,
            "duration": 1.702
        },
        {
            "text": "You look like a defeated man.",
            "start": 1035.334,
            "duration": 2.069
        },
        {
            "text": "Yeah, I busted the pool.",
            "start": 1037.436,
            "duration": 1.068
        },
        {
            "text": "How does one bust a pool?",
            "start": 1038.537,
            "duration": 1.034
        },
        {
            "text": "So I was driving by to drop off\nsome pallets, and I tried to turn,",
            "start": 1039.571,
            "duration": 3.637
        },
        {
            "text": "and it just turned the complete\nopposite way. I was like.",
            "start": 1043.242,
            "duration": 3.003
        },
        {
            "text": "No!",
            "start": 1046.278,
            "duration": 0.934
        },
        {
            "text": "So all this got wet?",
            "start": 1047.212,
            "duration": 0.868
        },
        {
            "text": "How many more weeks\ndo you have left?",
            "start": 1048.147,
            "duration": 1.301
        },
        {
            "text": "Weeks?",
            "start": 1049.481,
            "duration": 1.168
        },
        {
            "text": "I'm just taking it\nday by day right now.",
            "start": 1050.649,
            "duration": 2.102
        },
        {
            "text": "Depends how much longer I can go.",
            "start": 1052.785,
            "duration": 1.568
        },
        {
            "text": "So if you just see",
            "start": 1054.353,
            "duration": 0.634
        },
        {
            "text": "like a spider in your bed\ntomorrow, you're leaving?",
            "start": 1054.987,
            "duration": 2.235
        },
        {
            "text": "Oh, a hundred percent. Yeah.",
            "start": 1057.222,
            "duration": 1.202
        },
        {
            "text": "I don't think he has many days left.",
            "start": 1058.824,
            "duration": 1.668
        },
        {
            "text": "This is ending soon.",
            "start": 1060.492,
            "duration": 1.101
        },
        {
            "text": "You guys want to come hang out\nfor a little bit?",
            "start": 1061.627,
            "duration": 1.668
        },
        {
            "text": "- Heck no.\n- You're depressing.",
            "start": 1063.495,
            "duration": 1.235
        },
        {
            "text": "This is what the store looked like\nwhen Alex started the challenge.",
            "start": 1064.763,
            "duration": 3.037
        },
        {
            "text": "And this is what it looks like now.",
            "start": 1067.833,
            "duration": 2.703
        },
        {
            "text": "So day 44.",
            "start": 1073.939,
            "duration": 2.803
        },
        {
            "text": "It's almost dark outside.",
            "start": 1080.512,
            "duration": 1.435
        },
        {
            "text": "Jimmy hasn't come by today.",
            "start": 1082.347,
            "duration": 1.502
        },
        {
            "text": "I have stuff I need to sell.",
            "start": 1083.849,
            "duration": 2.069
        },
        {
            "text": "I'm just going to move\nthis stuff to the back.",
            "start": 1085.951,
            "duration": 2.035
        },
        {
            "text": "Hopefully somebody brings me\nthe $10,000 today.",
            "start": 1087.986,
            "duration": 3.27
        },
        {
            "text": "Maybe they just forgot or something.",
            "start": 1091.523,
            "duration": 1.869
        },
        {
            "text": "It's really lonely in here.",
            "start": 1096.128,
            "duration": 1.335
        },
        {
            "text": "I'm just going to",
            "start": 1098.997,
            "duration": 1.202
        },
        {
            "text": "go sit in my chair\ntill they bring me some money.",
            "start": 1100.199,
            "duration": 2.636
        },
        {
            "text": "Yo, what?",
            "start": 1110.676,
            "duration": 1.334
        },
        {
            "text": "Are you serious?",
            "start": 1112.344,
            "duration": 1.435
        },
        {
            "text": "Are you there, Jimmy?",
            "start": 1117.382,
            "duration": 1.168
        },
        {
            "text": "It's the first interaction\nI get all day, and it's...",
            "start": 1120.552,
            "duration": 2.903
        },
        {
            "text": "the freaking robot.",
            "start": 1124.389,
            "duration": 1.335
        },
        {
            "text": "Thanks for the money.",
            "start": 1127.693,
            "duration": 1.201
        },
        {
            "text": "Not even Jimmy\nwants to come here for a minute.",
            "start": 1135.367,
            "duration": 3.504
        },
        {
            "text": "That's how depressing this place is now.",
            "start": 1138.971,
            "duration": 2.068
        },
        {
            "text": "Can't say I blame him,\nhonestly.",
            "start": 1141.173,
            "duration": 1.868
        },
        {
            "text": "This sucks, man.",
            "start": 1144.309,
            "duration": 1.402
        },
        {
            "text": "God, I'm freaking miss my family\nso bad.",
            "start": 1168.033,
            "duration": 2.703
        },
        {
            "text": "It's day 45.",
            "start": 1171.103,
            "duration": 1.301
        },
        {
            "text": "And Chandler,\nhow would you say he's doing?",
            "start": 1172.404,
            "duration": 1.568
        },
        {
            "text": "That is complete boredom.\nHe's just tapping the bat on the ground.",
            "start": 1173.972,
            "duration": 2.87
        },
        {
            "text": "I would feel bad for him,\nexcept he's won $450,000,",
            "start": 1176.842,
            "duration": 4.538
        },
        {
            "text": "and he can leave whenever he wants,\nso he'll be fine.",
            "start": 1181.38,
            "duration": 3.303
        },
        {
            "text": "- Alex.\n- Hey.",
            "start": 1185.284,
            "duration": 1.635
        },
        {
            "text": "We were watching you on the cameras.",
            "start": 1186.952,
            "duration": 1.335
        },
        {
            "text": "You looked very sad.",
            "start": 1188.32,
            "duration": 1.268
        },
        {
            "text": "Yeah, I'm pretty bored.",
            "start": 1190.589,
            "duration": 1.101
        },
        {
            "text": "Well, here's $10,000.",
            "start": 1191.69,
            "duration": 1.235
        },
        {
            "text": "- So are you less bored?\n- Helps a little.",
            "start": 1192.925,
            "duration": 2.202
        },
        {
            "text": "How many weeks left you got?",
            "start": 1195.127,
            "duration": 1.501
        },
        {
            "text": "Well, I don't even know\nif I got an hour left, Jimmy.",
            "start": 1196.628,
            "duration": 1.869
        },
        {
            "text": "Really? Here, let's go look\nat your sea of money over here.",
            "start": 1198.53,
            "duration": 2.736
        },
        {
            "text": "This is all the money\nyou've made so far.",
            "start": 1201.266,
            "duration": 1.702
        },
        {
            "text": "450 grand.",
            "start": 1202.968,
            "duration": 1.235
        },
        {
            "text": "Are you saying\nyou're content with it?",
            "start": 1204.203,
            "duration": 1.568
        },
        {
            "text": "Give me one second.",
            "start": 1207.172,
            "duration": 0.868
        },
        {
            "text": "I've got a surprise\nthat might help you decide.",
            "start": 1208.04,
            "duration": 2.335
        },
        {
            "text": "What? Are you serious?",
            "start": 1210.742,
            "duration": 1.969
        },
        {
            "text": "Hey babe.",
            "start": 1215.047,
            "duration": 0.934
        },
        {
            "text": "What the heck?",
            "start": 1216.014,
            "duration": 1.135
        },
        {
            "text": "Don't cry.",
            "start": 1217.182,
            "duration": 1.301
        },
        {
            "text": "I can't help it.",
            "start": 1219.651,
            "duration": 1.402
        },
        {
            "text": "Okay.",
            "start": 1222.821,
            "duration": 0.801
        },
        {
            "text": "Why aren't you wearing your shoes?",
            "start": 1223.655,
            "duration": 1.402
        },
        {
            "text": "And your shirt?",
            "start": 1225.757,
            "duration": 1.001
        },
        {
            "text": "To be clear,\nI didn't take his shoes.",
            "start": 1226.758,
            "duration": 2.536
        },
        {
            "text": "I don't know why he's not wearing\nshoes.",
            "start": 1229.294,
            "duration": 1.568
        },
        {
            "text": "These are all the things that\nthis money's going to go toward.",
            "start": 1230.862,
            "duration": 2.603
        },
        {
            "text": "- Isn't this crazy?\n- I can't even wrap my head around it.",
            "start": 1233.498,
            "duration": 2.002
        },
        {
            "text": "I feel like I could do another\nfive days.",
            "start": 1235.534,
            "duration": 2.836
        },
        {
            "text": "Do you think it's worth it?",
            "start": 1238.37,
            "duration": 1.335
        },
        {
            "text": "What's the verdict?",
            "start": 1241.34,
            "duration": 0.967
        },
        {
            "text": "- We've weighed the options.\n- Make tons of money.",
            "start": 1242.341,
            "duration": 1.902
        },
        {
            "text": "Keep tons of money already made.",
            "start": 1244.276,
            "duration": 1.568
        },
        {
            "text": "Honestly, it's not worth staying\nand I\u2019m leaving.",
            "start": 1245.844,
            "duration": 2.903
        },
        {
            "text": "Okay, well,\nthen let's push the money out.",
            "start": 1248.78,
            "duration": 2.636
        },
        {
            "text": "All right, Alex, the second\nyou step on the red, it's over.",
            "start": 1256.188,
            "duration": 3.203
        },
        {
            "text": "I can move all the money back.\nWe can keep going.",
            "start": 1259.391,
            "duration": 2.069
        },
        {
            "text": "It's your decision.",
            "start": 1261.493,
            "duration": 1.201
        },
        {
            "text": "All right, bring it back in.",
            "start": 1263.962,
            "duration": 1.068
        },
        {
            "text": "Okay, bring it back in.",
            "start": 1265.03,
            "duration": 1.235
        },
        {
            "text": "Just kidding.",
            "start": 1266.598,
            "duration": 0.868
        },
        {
            "text": "Let's go!",
            "start": 1269.568,
            "duration": 1.001
        },
        {
            "text": "Alex spent 45 days in the store\nand walked away with $450,000.",
            "start": 1270.636,
            "duration": 4.738
        },
        {
            "text": "Can't believe this happened.\nThis is freaking sick.",
            "start": 1275.44,
            "duration": 3.404
        },
        {
            "text": "Congratulations, Alex.",
            "start": 1279.044,
            "duration": 1.468
        },
        {
            "text": "Shout out to Albertsons for helping us\nfill the shelves.",
            "start": 1280.512,
            "duration": 1.902
        },
        {
            "text": "You guys are amazing.\n I'm going to go find him a shirt.",
            "start": 1282.414,
            "duration": 2.302
        },
        {
            "text": "Also, if you're wondering\nhow we filmed this video",
            "start": 1284.716,
            "duration": 1.702
        },
        {
            "text": "because we blew up\nthe earth earlier,",
            "start": 1286.418,
            "duration": 1.501
        },
        {
            "text": "it was actually on the moon\nthe entire time.",
            "start": 1287.919,
            "duration": 1.736
        },
        {
            "text": "Watch the laser\nmaze video if that's confusing.",
            "start": 1289.655,
            "duration": 1.868
        }
    ],
    "stats": {
        "viewCount": "257306885",
        "likeCount": "5855597",
        "favoriteCount": "0",
        "commentCount": "84167"
    }
}